{
 "Alpha-3 code":"ERI",
 "Country or Area":"Eritrea",
 "Latitude (average)":15.0,
 "Longitude (average)":39.0,
 "Group 1":"Africa",
 "Group 2":"Sub-Saharan Africa",
 "LDC":true,
 "LLDC":false,
 "SIDS":false,
 "Income group":"Low income",
 "UNDP_Region":"UNDP_SSA",
 "indicators":[
  {
   "indicator":"ambientparticulatematterpollutionexposure_apmattpe",
   "yearlyData":[
    {
     "year":1990,
     "value":45.0
    },
    {
     "year":1995,
     "value":41.78
    },
    {
     "year":2000,
     "value":44.92
    },
    {
     "year":2005,
     "value":42.14
    },
    {
     "year":2010,
     "value":43.29
    },
    {
     "year":2011,
     "value":43.39
    },
    {
     "year":2012,
     "value":44.54
    },
    {
     "year":2013,
     "value":44.71
    },
    {
     "year":2014,
     "value":39.15
    },
    {
     "year":2015,
     "value":43.07
    },
    {
     "year":2016,
     "value":41.33
    },
    {
     "year":2017,
     "value":43.85
    },
    {
     "year":2018,
     "value":43.48
    },
    {
     "year":2019,
     "value":44.07
    }
   ]
  },
  {
   "indicator":"bedsformentalhealthingeneralhospital_bedsmhgh",
   "yearlyData":[
    {
     "year":2016,
     "value":0.41
    }
   ]
  },
  {
   "indicator":"bedsinmentalhospitals_bedsmh",
   "yearlyData":[
    {
     "year":2016,
     "value":4.13
    }
   ]
  },
  {
   "indicator":"changeinabsolutenumberofpeopleexposedtocoastalfloods_informcc",
   "yearlyData":[
    {
     "year":2050,
     "value":45.61
    }
   ]
  },
  {
   "indicator":"changeinabsolutenumberofpeopleexposedtodrought_informcc",
   "yearlyData":[
    {
     "year":2050,
     "value":2129035.3799999999
    }
   ]
  },
  {
   "indicator":"changeinabsolutenumberofpeopleexposedtofloods_informcc",
   "yearlyData":[
    {
     "year":2050,
     "value":20656.12
    }
   ]
  },
  {
   "indicator":"changeinabsolutenumberofpeopleexposedtomalariaanddengue_informcc",
   "yearlyData":[
    {
     "year":2050,
     "value":8793573.3900000006
    }
   ]
  },
  {
   "indicator":"changeinhumanhazardandexposuretoconflict_informcc",
   "yearlyData":[
    {
     "year":2050,
     "value":1.3
    }
   ]
  },
  {
   "indicator":"chemicalevents_chemevents",
   "yearlyData":[
    {
     "year":2018,
     "value":20.0
    },
    {
     "year":2019,
     "value":20.0
    },
    {
     "year":2020,
     "value":20.0
    }
   ]
  },
  {
   "indicator":"coverageofprotectedareasinrelationtomarineareas_ermrmmpa",
   "yearlyData":[
    {
     "year":2000,
     "value":0.0
    },
    {
     "year":2001,
     "value":0.0
    },
    {
     "year":2002,
     "value":0.0
    },
    {
     "year":2003,
     "value":0.0
    },
    {
     "year":2004,
     "value":0.0
    },
    {
     "year":2005,
     "value":0.0
    },
    {
     "year":2006,
     "value":0.0
    },
    {
     "year":2007,
     "value":0.0
    },
    {
     "year":2008,
     "value":0.0
    },
    {
     "year":2009,
     "value":0.0
    },
    {
     "year":2010,
     "value":0.0
    },
    {
     "year":2011,
     "value":0.0
    },
    {
     "year":2012,
     "value":0.0
    },
    {
     "year":2013,
     "value":0.0
    },
    {
     "year":2014,
     "value":0.0
    },
    {
     "year":2015,
     "value":0.0
    },
    {
     "year":2016,
     "value":0.0
    },
    {
     "year":2017,
     "value":0.0
    },
    {
     "year":2018,
     "value":0.0
    },
    {
     "year":2019,
     "value":0.0
    },
    {
     "year":2020,
     "value":0.0
    },
    {
     "year":2021,
     "value":0.0
    },
    {
     "year":2022,
     "value":0.0
    }
   ]
  },
  {
   "indicator":"deathsattributedtocardiovasculardiseasesfemale_dcdfihme",
   "yearlyData":[
    {
     "year":1990,
     "value":91.4
    },
    {
     "year":1991,
     "value":91.89
    },
    {
     "year":1992,
     "value":89.38
    },
    {
     "year":1993,
     "value":87.26
    },
    {
     "year":1994,
     "value":87.06
    },
    {
     "year":1995,
     "value":87.53
    },
    {
     "year":1996,
     "value":86.86
    },
    {
     "year":1997,
     "value":86.86
    },
    {
     "year":1998,
     "value":86.36
    },
    {
     "year":1999,
     "value":86.91
    },
    {
     "year":2000,
     "value":87.22
    },
    {
     "year":2001,
     "value":86.04
    },
    {
     "year":2002,
     "value":87.24
    },
    {
     "year":2003,
     "value":87.69
    },
    {
     "year":2004,
     "value":89.02
    },
    {
     "year":2005,
     "value":89.85
    },
    {
     "year":2006,
     "value":90.71
    },
    {
     "year":2007,
     "value":91.5
    },
    {
     "year":2008,
     "value":92.73
    },
    {
     "year":2009,
     "value":93.54
    },
    {
     "year":2010,
     "value":94.34
    },
    {
     "year":2011,
     "value":95.05
    },
    {
     "year":2012,
     "value":96.62
    },
    {
     "year":2013,
     "value":98.29
    },
    {
     "year":2014,
     "value":99.46
    },
    {
     "year":2015,
     "value":101.27
    },
    {
     "year":2016,
     "value":102.44
    },
    {
     "year":2017,
     "value":103.72
    },
    {
     "year":2018,
     "value":104.85
    },
    {
     "year":2019,
     "value":105.86
    }
   ]
  },
  {
   "indicator":"deathsattributedtocardiovasculardiseasesmale_dcdmihme",
   "yearlyData":[
    {
     "year":1990,
     "value":99.65
    },
    {
     "year":1991,
     "value":100.22
    },
    {
     "year":1992,
     "value":98.71
    },
    {
     "year":1993,
     "value":98.02
    },
    {
     "year":1994,
     "value":99.28
    },
    {
     "year":1995,
     "value":104.04
    },
    {
     "year":1996,
     "value":101.59
    },
    {
     "year":1997,
     "value":99.3
    },
    {
     "year":1998,
     "value":95.94
    },
    {
     "year":1999,
     "value":94.44
    },
    {
     "year":2000,
     "value":92.64
    },
    {
     "year":2001,
     "value":89.77
    },
    {
     "year":2002,
     "value":90.13
    },
    {
     "year":2003,
     "value":89.32
    },
    {
     "year":2004,
     "value":89.46
    },
    {
     "year":2005,
     "value":89.09
    },
    {
     "year":2006,
     "value":88.89
    },
    {
     "year":2007,
     "value":88.46
    },
    {
     "year":2008,
     "value":88.53
    },
    {
     "year":2009,
     "value":88.23
    },
    {
     "year":2010,
     "value":87.99
    },
    {
     "year":2011,
     "value":87.8
    },
    {
     "year":2012,
     "value":88.2
    },
    {
     "year":2013,
     "value":88.58
    },
    {
     "year":2014,
     "value":88.74
    },
    {
     "year":2015,
     "value":89.89
    },
    {
     "year":2016,
     "value":90.17
    },
    {
     "year":2017,
     "value":90.81
    },
    {
     "year":2018,
     "value":91.83
    },
    {
     "year":2019,
     "value":92.7
    }
   ]
  },
  {
   "indicator":"deathsattributedtochronicrespiratorydiseasesfemale_dcrdfihme",
   "yearlyData":[
    {
     "year":1990,
     "value":21.53
    },
    {
     "year":1991,
     "value":21.39
    },
    {
     "year":1992,
     "value":20.51
    },
    {
     "year":1993,
     "value":19.64
    },
    {
     "year":1994,
     "value":19.15
    },
    {
     "year":1995,
     "value":18.8
    },
    {
     "year":1996,
     "value":18.3
    },
    {
     "year":1997,
     "value":17.97
    },
    {
     "year":1998,
     "value":17.53
    },
    {
     "year":1999,
     "value":17.36
    },
    {
     "year":2000,
     "value":17.14
    },
    {
     "year":2001,
     "value":16.62
    },
    {
     "year":2002,
     "value":16.7
    },
    {
     "year":2003,
     "value":16.57
    },
    {
     "year":2004,
     "value":16.79
    },
    {
     "year":2005,
     "value":16.74
    },
    {
     "year":2006,
     "value":16.65
    },
    {
     "year":2007,
     "value":16.57
    },
    {
     "year":2008,
     "value":16.57
    },
    {
     "year":2009,
     "value":16.41
    },
    {
     "year":2010,
     "value":16.37
    },
    {
     "year":2011,
     "value":16.28
    },
    {
     "year":2012,
     "value":16.32
    },
    {
     "year":2013,
     "value":16.44
    },
    {
     "year":2014,
     "value":16.47
    },
    {
     "year":2015,
     "value":16.52
    },
    {
     "year":2016,
     "value":16.54
    },
    {
     "year":2017,
     "value":16.45
    },
    {
     "year":2018,
     "value":16.37
    },
    {
     "year":2019,
     "value":16.35
    }
   ]
  },
  {
   "indicator":"deathsattributedtochronicrespiratorydiseasesmale_dcrdmihme",
   "yearlyData":[
    {
     "year":1990,
     "value":25.39
    },
    {
     "year":1991,
     "value":25.37
    },
    {
     "year":1992,
     "value":24.63
    },
    {
     "year":1993,
     "value":24.12
    },
    {
     "year":1994,
     "value":24.06
    },
    {
     "year":1995,
     "value":24.83
    },
    {
     "year":1996,
     "value":24.1
    },
    {
     "year":1997,
     "value":23.43
    },
    {
     "year":1998,
     "value":22.5
    },
    {
     "year":1999,
     "value":22.03
    },
    {
     "year":2000,
     "value":21.4
    },
    {
     "year":2001,
     "value":20.45
    },
    {
     "year":2002,
     "value":20.24
    },
    {
     "year":2003,
     "value":19.83
    },
    {
     "year":2004,
     "value":19.74
    },
    {
     "year":2005,
     "value":19.46
    },
    {
     "year":2006,
     "value":19.21
    },
    {
     "year":2007,
     "value":18.93
    },
    {
     "year":2008,
     "value":18.75
    },
    {
     "year":2009,
     "value":18.45
    },
    {
     "year":2010,
     "value":18.23
    },
    {
     "year":2011,
     "value":18.01
    },
    {
     "year":2012,
     "value":17.86
    },
    {
     "year":2013,
     "value":17.73
    },
    {
     "year":2014,
     "value":17.55
    },
    {
     "year":2015,
     "value":17.47
    },
    {
     "year":2016,
     "value":17.31
    },
    {
     "year":2017,
     "value":17.12
    },
    {
     "year":2018,
     "value":17.02
    },
    {
     "year":2019,
     "value":16.92
    }
   ]
  },
  {
   "indicator":"deathsattributedtodigestivediseasesfemale_dddfihme",
   "yearlyData":[
    {
     "year":1990,
     "value":24.06
    },
    {
     "year":1991,
     "value":24.27
    },
    {
     "year":1992,
     "value":23.96
    },
    {
     "year":1993,
     "value":23.69
    },
    {
     "year":1994,
     "value":23.86
    },
    {
     "year":1995,
     "value":24.22
    },
    {
     "year":1996,
     "value":24.29
    },
    {
     "year":1997,
     "value":24.58
    },
    {
     "year":1998,
     "value":24.69
    },
    {
     "year":1999,
     "value":25.29
    },
    {
     "year":2000,
     "value":25.79
    },
    {
     "year":2001,
     "value":25.63
    },
    {
     "year":2002,
     "value":26.42
    },
    {
     "year":2003,
     "value":26.63
    },
    {
     "year":2004,
     "value":27.22
    },
    {
     "year":2005,
     "value":27.43
    },
    {
     "year":2006,
     "value":27.52
    },
    {
     "year":2007,
     "value":27.56
    },
    {
     "year":2008,
     "value":27.77
    },
    {
     "year":2009,
     "value":27.78
    },
    {
     "year":2010,
     "value":27.82
    },
    {
     "year":2011,
     "value":27.82
    },
    {
     "year":2012,
     "value":28.01
    },
    {
     "year":2013,
     "value":28.4
    },
    {
     "year":2014,
     "value":28.52
    },
    {
     "year":2015,
     "value":28.82
    },
    {
     "year":2016,
     "value":29.07
    },
    {
     "year":2017,
     "value":29.33
    },
    {
     "year":2018,
     "value":29.29
    },
    {
     "year":2019,
     "value":29.38
    }
   ]
  },
  {
   "indicator":"deathsattributedtodigestivediseasesmale_dddmihme",
   "yearlyData":[
    {
     "year":1990,
     "value":40.96
    },
    {
     "year":1991,
     "value":41.56
    },
    {
     "year":1992,
     "value":41.53
    },
    {
     "year":1993,
     "value":41.79
    },
    {
     "year":1994,
     "value":42.87
    },
    {
     "year":1995,
     "value":45.37
    },
    {
     "year":1996,
     "value":45.06
    },
    {
     "year":1997,
     "value":44.96
    },
    {
     "year":1998,
     "value":44.27
    },
    {
     "year":1999,
     "value":44.71
    },
    {
     "year":2000,
     "value":44.83
    },
    {
     "year":2001,
     "value":43.9
    },
    {
     "year":2002,
     "value":44.88
    },
    {
     "year":2003,
     "value":44.81
    },
    {
     "year":2004,
     "value":45.29
    },
    {
     "year":2005,
     "value":45.2
    },
    {
     "year":2006,
     "value":45.0
    },
    {
     "year":2007,
     "value":44.66
    },
    {
     "year":2008,
     "value":44.64
    },
    {
     "year":2009,
     "value":44.36
    },
    {
     "year":2010,
     "value":44.05
    },
    {
     "year":2011,
     "value":43.72
    },
    {
     "year":2012,
     "value":43.67
    },
    {
     "year":2013,
     "value":43.8
    },
    {
     "year":2014,
     "value":43.73
    },
    {
     "year":2015,
     "value":44.04
    },
    {
     "year":2016,
     "value":44.13
    },
    {
     "year":2017,
     "value":44.36
    },
    {
     "year":2018,
     "value":44.54
    },
    {
     "year":2019,
     "value":44.78
    }
   ]
  },
  {
   "indicator":"deathsattributedtoneurologicaldisordersfemale_dndfihme",
   "yearlyData":[
    {
     "year":1990,
     "value":4.75
    },
    {
     "year":1991,
     "value":4.89
    },
    {
     "year":1992,
     "value":4.88
    },
    {
     "year":1993,
     "value":4.89
    },
    {
     "year":1994,
     "value":4.96
    },
    {
     "year":1995,
     "value":5.07
    },
    {
     "year":1996,
     "value":5.16
    },
    {
     "year":1997,
     "value":5.3
    },
    {
     "year":1998,
     "value":5.43
    },
    {
     "year":1999,
     "value":5.61
    },
    {
     "year":2000,
     "value":5.75
    },
    {
     "year":2001,
     "value":5.75
    },
    {
     "year":2002,
     "value":5.9
    },
    {
     "year":2003,
     "value":6.01
    },
    {
     "year":2004,
     "value":6.2
    },
    {
     "year":2005,
     "value":6.31
    },
    {
     "year":2006,
     "value":6.39
    },
    {
     "year":2007,
     "value":6.49
    },
    {
     "year":2008,
     "value":6.59
    },
    {
     "year":2009,
     "value":6.66
    },
    {
     "year":2010,
     "value":6.76
    },
    {
     "year":2011,
     "value":6.87
    },
    {
     "year":2012,
     "value":7.04
    },
    {
     "year":2013,
     "value":7.25
    },
    {
     "year":2014,
     "value":7.45
    },
    {
     "year":2015,
     "value":7.67
    },
    {
     "year":2016,
     "value":7.88
    },
    {
     "year":2017,
     "value":8.06
    },
    {
     "year":2018,
     "value":8.24
    },
    {
     "year":2019,
     "value":8.4
    }
   ]
  },
  {
   "indicator":"deathsattributedtoneurologicaldisordersmale_dndmihme",
   "yearlyData":[
    {
     "year":1990,
     "value":4.57
    },
    {
     "year":1991,
     "value":4.65
    },
    {
     "year":1992,
     "value":4.62
    },
    {
     "year":1993,
     "value":4.63
    },
    {
     "year":1994,
     "value":4.74
    },
    {
     "year":1995,
     "value":5.01
    },
    {
     "year":1996,
     "value":5.0
    },
    {
     "year":1997,
     "value":5.04
    },
    {
     "year":1998,
     "value":5.01
    },
    {
     "year":1999,
     "value":5.13
    },
    {
     "year":2000,
     "value":5.19
    },
    {
     "year":2001,
     "value":5.08
    },
    {
     "year":2002,
     "value":5.27
    },
    {
     "year":2003,
     "value":5.3
    },
    {
     "year":2004,
     "value":5.43
    },
    {
     "year":2005,
     "value":5.43
    },
    {
     "year":2006,
     "value":5.43
    },
    {
     "year":2007,
     "value":5.41
    },
    {
     "year":2008,
     "value":5.42
    },
    {
     "year":2009,
     "value":5.38
    },
    {
     "year":2010,
     "value":5.36
    },
    {
     "year":2011,
     "value":5.36
    },
    {
     "year":2012,
     "value":5.41
    },
    {
     "year":2013,
     "value":5.49
    },
    {
     "year":2014,
     "value":5.55
    },
    {
     "year":2015,
     "value":5.64
    },
    {
     "year":2016,
     "value":5.71
    },
    {
     "year":2017,
     "value":5.76
    },
    {
     "year":2018,
     "value":5.85
    },
    {
     "year":2019,
     "value":5.94
    }
   ]
  },
  {
   "indicator":"deathsattributedtononcommunicablediseasesfemale_doncdfihme",
   "yearlyData":[
    {
     "year":1990,
     "value":25.71
    },
    {
     "year":1991,
     "value":25.28
    },
    {
     "year":1992,
     "value":24.34
    },
    {
     "year":1993,
     "value":23.48
    },
    {
     "year":1994,
     "value":22.84
    },
    {
     "year":1995,
     "value":22.29
    },
    {
     "year":1996,
     "value":21.88
    },
    {
     "year":1997,
     "value":21.63
    },
    {
     "year":1998,
     "value":21.36
    },
    {
     "year":1999,
     "value":21.16
    },
    {
     "year":2000,
     "value":21.22
    },
    {
     "year":2001,
     "value":21.2
    },
    {
     "year":2002,
     "value":21.55
    },
    {
     "year":2003,
     "value":21.38
    },
    {
     "year":2004,
     "value":22.09
    },
    {
     "year":2005,
     "value":21.94
    },
    {
     "year":2006,
     "value":21.44
    },
    {
     "year":2007,
     "value":20.98
    },
    {
     "year":2008,
     "value":20.33
    },
    {
     "year":2009,
     "value":19.2
    },
    {
     "year":2010,
     "value":18.59
    },
    {
     "year":2011,
     "value":17.98
    },
    {
     "year":2012,
     "value":17.45
    },
    {
     "year":2013,
     "value":17.36
    },
    {
     "year":2014,
     "value":17.12
    },
    {
     "year":2015,
     "value":16.91
    },
    {
     "year":2016,
     "value":16.62
    },
    {
     "year":2017,
     "value":15.94
    },
    {
     "year":2018,
     "value":15.45
    },
    {
     "year":2019,
     "value":15.3
    }
   ]
  },
  {
   "indicator":"deathsattributedtononcommunicablediseasesmale_doncdmihme",
   "yearlyData":[
    {
     "year":1990,
     "value":33.33
    },
    {
     "year":1991,
     "value":32.73
    },
    {
     "year":1992,
     "value":31.56
    },
    {
     "year":1993,
     "value":30.85
    },
    {
     "year":1994,
     "value":30.32
    },
    {
     "year":1995,
     "value":30.14
    },
    {
     "year":1996,
     "value":29.9
    },
    {
     "year":1997,
     "value":29.73
    },
    {
     "year":1998,
     "value":29.43
    },
    {
     "year":1999,
     "value":29.3
    },
    {
     "year":2000,
     "value":29.27
    },
    {
     "year":2001,
     "value":28.99
    },
    {
     "year":2002,
     "value":29.15
    },
    {
     "year":2003,
     "value":28.79
    },
    {
     "year":2004,
     "value":29.41
    },
    {
     "year":2005,
     "value":29.06
    },
    {
     "year":2006,
     "value":28.34
    },
    {
     "year":2007,
     "value":27.64
    },
    {
     "year":2008,
     "value":26.85
    },
    {
     "year":2009,
     "value":25.51
    },
    {
     "year":2010,
     "value":24.56
    },
    {
     "year":2011,
     "value":23.71
    },
    {
     "year":2012,
     "value":22.95
    },
    {
     "year":2013,
     "value":22.59
    },
    {
     "year":2014,
     "value":22.11
    },
    {
     "year":2015,
     "value":21.76
    },
    {
     "year":2016,
     "value":21.25
    },
    {
     "year":2017,
     "value":20.45
    },
    {
     "year":2018,
     "value":19.84
    },
    {
     "year":2019,
     "value":19.6
    }
   ]
  },
  {
   "indicator":"degreeofimplementationofinternationalinstrumentsaimingtocombatillegalunreportedunregulatedfishing_ilfish",
   "yearlyData":[
    {
     "year":2020,
     "value":2.0
    },
    {
     "year":2022,
     "value":2.0
    }
   ]
  },
  {
   "indicator":"forestareatothepercentageoflandarea_frstarea",
   "yearlyData":[
    {
     "year":1993,
     "value":11.29
    },
    {
     "year":1994,
     "value":11.26
    },
    {
     "year":1995,
     "value":11.23
    },
    {
     "year":1996,
     "value":11.2
    },
    {
     "year":1997,
     "value":11.17
    },
    {
     "year":1998,
     "value":11.14
    },
    {
     "year":1999,
     "value":11.11
    },
    {
     "year":2000,
     "value":11.07
    },
    {
     "year":2001,
     "value":11.04
    },
    {
     "year":2002,
     "value":11.01
    },
    {
     "year":2003,
     "value":10.98
    },
    {
     "year":2004,
     "value":9.14
    },
    {
     "year":2005,
     "value":9.11
    },
    {
     "year":2006,
     "value":9.09
    },
    {
     "year":2007,
     "value":9.06
    },
    {
     "year":2008,
     "value":9.03
    },
    {
     "year":2009,
     "value":9.0
    },
    {
     "year":2010,
     "value":8.98
    },
    {
     "year":2011,
     "value":8.95
    },
    {
     "year":2012,
     "value":8.92
    },
    {
     "year":2013,
     "value":8.9
    },
    {
     "year":2014,
     "value":8.88
    },
    {
     "year":2015,
     "value":8.85
    },
    {
     "year":2016,
     "value":8.82
    },
    {
     "year":2017,
     "value":8.79
    },
    {
     "year":2018,
     "value":8.77
    },
    {
     "year":2019,
     "value":8.74
    },
    {
     "year":2020,
     "value":8.72
    }
   ]
  },
  {
   "indicator":"gghedaspercentageofgge_gghedgge",
   "yearlyData":[
    {
     "year":2000,
     "value":2.14
    },
    {
     "year":2001,
     "value":2.01
    },
    {
     "year":2002,
     "value":2.62
    },
    {
     "year":2003,
     "value":1.93
    },
    {
     "year":2004,
     "value":2.2
    },
    {
     "year":2005,
     "value":1.15
    },
    {
     "year":2006,
     "value":1.54
    },
    {
     "year":2007,
     "value":2.35
    },
    {
     "year":2008,
     "value":2.35
    },
    {
     "year":2009,
     "value":2.35
    },
    {
     "year":2010,
     "value":2.35
    },
    {
     "year":2011,
     "value":2.35
    },
    {
     "year":2012,
     "value":2.35
    },
    {
     "year":2013,
     "value":2.35
    },
    {
     "year":2014,
     "value":2.35
    },
    {
     "year":2015,
     "value":2.35
    },
    {
     "year":2016,
     "value":2.35
    },
    {
     "year":2017,
     "value":2.35
    },
    {
     "year":2018,
     "value":2.35
    },
    {
     "year":2019,
     "value":2.35
    },
    {
     "year":2020,
     "value":2.35
    }
   ]
  },
  {
   "indicator":"governmentexpenditureontotaleducation_wdi",
   "yearlyData":[
    {
     "year":1996,
     "value":1.64
    },
    {
     "year":1998,
     "value":4.62
    },
    {
     "year":1999,
     "value":5.26
    },
    {
     "year":2001,
     "value":4.05
    },
    {
     "year":2002,
     "value":3.52
    },
    {
     "year":2004,
     "value":3.15
    },
    {
     "year":2006,
     "value":2.13
    }
   ]
  },
  {
   "indicator":"hivprevalenceamongprisoners_transgp",
   "yearlyData":[
    {
     "year":2015,
     "value":2.5
    },
    {
     "year":2017,
     "value":1.3
    },
    {
     "year":2019,
     "value":1.4
    }
   ]
  },
  {
   "indicator":"householdairpolutionfromsolidfuels_hapsfuel",
   "yearlyData":[
    {
     "year":1990,
     "value":0.84
    },
    {
     "year":1991,
     "value":0.83
    },
    {
     "year":1992,
     "value":0.83
    },
    {
     "year":1993,
     "value":0.81
    },
    {
     "year":1994,
     "value":0.8
    },
    {
     "year":1995,
     "value":0.79
    },
    {
     "year":1996,
     "value":0.78
    },
    {
     "year":1997,
     "value":0.77
    },
    {
     "year":1998,
     "value":0.75
    },
    {
     "year":1999,
     "value":0.74
    },
    {
     "year":2000,
     "value":0.73
    },
    {
     "year":2001,
     "value":0.72
    },
    {
     "year":2002,
     "value":0.71
    },
    {
     "year":2003,
     "value":0.72
    },
    {
     "year":2004,
     "value":0.72
    },
    {
     "year":2005,
     "value":0.73
    },
    {
     "year":2006,
     "value":0.73
    },
    {
     "year":2007,
     "value":0.74
    },
    {
     "year":2008,
     "value":0.75
    },
    {
     "year":2009,
     "value":0.75
    },
    {
     "year":2010,
     "value":0.75
    },
    {
     "year":2011,
     "value":0.75
    },
    {
     "year":2012,
     "value":0.75
    },
    {
     "year":2013,
     "value":0.75
    },
    {
     "year":2014,
     "value":0.74
    },
    {
     "year":2015,
     "value":0.73
    },
    {
     "year":2016,
     "value":0.72
    },
    {
     "year":2017,
     "value":0.71
    },
    {
     "year":2018,
     "value":0.69
    },
    {
     "year":2019,
     "value":0.68
    }
   ]
  },
  {
   "indicator":"mentalhealthoutpatientfacilities_mhof",
   "yearlyData":[
    {
     "year":2016,
     "value":0.23
    }
   ]
  },
  {
   "indicator":"mentalhealthunitsingeneralhospitals_mhugh",
   "yearlyData":[
    {
     "year":2016,
     "value":0.21
    }
   ]
  },
  {
   "indicator":"mothertochildhivtransmissionrate_mchvitr",
   "yearlyData":[
    {
     "year":2000,
     "value":48.12
    },
    {
     "year":2001,
     "value":46.07
    },
    {
     "year":2002,
     "value":44.78
    },
    {
     "year":2003,
     "value":44.54
    },
    {
     "year":2004,
     "value":43.44
    },
    {
     "year":2005,
     "value":39.17
    },
    {
     "year":2006,
     "value":40.2
    },
    {
     "year":2007,
     "value":32.67
    },
    {
     "year":2008,
     "value":31.55
    },
    {
     "year":2009,
     "value":31.51
    },
    {
     "year":2010,
     "value":29.16
    },
    {
     "year":2011,
     "value":26.51
    },
    {
     "year":2012,
     "value":20.74
    },
    {
     "year":2013,
     "value":19.83
    },
    {
     "year":2014,
     "value":17.16
    },
    {
     "year":2015,
     "value":14.74
    },
    {
     "year":2016,
     "value":18.56
    },
    {
     "year":2017,
     "value":16.06
    },
    {
     "year":2018,
     "value":11.41
    },
    {
     "year":2019,
     "value":15.02
    },
    {
     "year":2020,
     "value":10.81
    },
    {
     "year":2021,
     "value":15.53
    }
   ]
  },
  {
   "indicator":"numofpregnantwomanwithhivneedingantiretrovirals_hivpwnpmtct",
   "yearlyData":[
    {
     "year":1990,
     "value":500.0
    },
    {
     "year":1991,
     "value":500.0
    },
    {
     "year":1992,
     "value":500.0
    },
    {
     "year":1993,
     "value":510.0
    },
    {
     "year":1994,
     "value":590.0
    },
    {
     "year":1995,
     "value":620.0
    },
    {
     "year":1996,
     "value":740.0
    },
    {
     "year":1997,
     "value":720.0
    },
    {
     "year":1998,
     "value":690.0
    },
    {
     "year":1999,
     "value":650.0
    },
    {
     "year":2000,
     "value":630.0
    },
    {
     "year":2001,
     "value":580.0
    },
    {
     "year":2002,
     "value":580.0
    },
    {
     "year":2003,
     "value":550.0
    },
    {
     "year":2004,
     "value":540.0
    },
    {
     "year":2005,
     "value":510.0
    },
    {
     "year":2006,
     "value":500.0
    },
    {
     "year":2007,
     "value":500.0
    },
    {
     "year":2008,
     "value":500.0
    },
    {
     "year":2009,
     "value":500.0
    },
    {
     "year":2010,
     "value":500.0
    },
    {
     "year":2011,
     "value":500.0
    },
    {
     "year":2012,
     "value":500.0
    },
    {
     "year":2013,
     "value":500.0
    },
    {
     "year":2014,
     "value":500.0
    },
    {
     "year":2015,
     "value":500.0
    },
    {
     "year":2016,
     "value":500.0
    },
    {
     "year":2017,
     "value":500.0
    },
    {
     "year":2018,
     "value":500.0
    },
    {
     "year":2019,
     "value":500.0
    },
    {
     "year":2020,
     "value":200.0
    },
    {
     "year":2021,
     "value":200.0
    },
    {
     "year":2022,
     "value":200.0
    }
   ]
  },
  {
   "indicator":"numofpregnantwomenwithhivreceivedantiretrovirals_hivpwrapmtct",
   "yearlyData":[
    {
     "year":2010,
     "value":37.0
    },
    {
     "year":2011,
     "value":60.0
    },
    {
     "year":2012,
     "value":100.0
    },
    {
     "year":2013,
     "value":100.0
    },
    {
     "year":2014,
     "value":100.0
    },
    {
     "year":2015,
     "value":100.0
    },
    {
     "year":2016,
     "value":80.0
    },
    {
     "year":2017,
     "value":91.0
    },
    {
     "year":2018,
     "value":100.0
    },
    {
     "year":2019,
     "value":89.0
    },
    {
     "year":2020,
     "value":100.0
    },
    {
     "year":2021,
     "value":84.0
    },
    {
     "year":2022,
     "value":93.0
    }
   ]
  },
  {
   "indicator":"nursesworkinginmentalhealthsector_nursmhs",
   "yearlyData":[
    {
     "year":2016,
     "value":2.17
    }
   ]
  },
  {
   "indicator":"percentageofgirlsundergonefemalegenitalmalfunctionsagebelow15_fgmua",
   "yearlyData":[
    {
     "year":2010,
     "value":33.2
    }
   ]
  },
  {
   "indicator":"percentageofgirlsundergonefemalegenitalmalfunctionsagebetween15to49_fgmafa",
   "yearlyData":[
    {
     "year":2010,
     "value":83.0
    }
   ]
  },
  {
   "indicator":"percentofterrestrialprotectedareasoftotallandareas_trrprotarea",
   "yearlyData":[
    {
     "year":2016,
     "value":4.87
    },
    {
     "year":2017,
     "value":4.87
    },
    {
     "year":2018,
     "value":4.87
    },
    {
     "year":2019,
     "value":4.87
    },
    {
     "year":2020,
     "value":4.87
    },
    {
     "year":2021,
     "value":0.0
    },
    {
     "year":2022,
     "value":0.0
    }
   ]
  },
  {
   "indicator":"prevalencealcoholandsubstanceusedisordersbothsexes_pasdis",
   "yearlyData":[
    {
     "year":1990,
     "value":1.97
    },
    {
     "year":1991,
     "value":1.97
    },
    {
     "year":1992,
     "value":1.96
    },
    {
     "year":1993,
     "value":1.96
    },
    {
     "year":1994,
     "value":1.96
    },
    {
     "year":1995,
     "value":1.96
    },
    {
     "year":1996,
     "value":1.96
    },
    {
     "year":1997,
     "value":1.96
    },
    {
     "year":1998,
     "value":1.96
    },
    {
     "year":1999,
     "value":1.97
    },
    {
     "year":2000,
     "value":1.97
    },
    {
     "year":2001,
     "value":1.97
    },
    {
     "year":2002,
     "value":1.97
    },
    {
     "year":2003,
     "value":1.97
    },
    {
     "year":2004,
     "value":1.96
    },
    {
     "year":2005,
     "value":1.97
    },
    {
     "year":2006,
     "value":1.97
    },
    {
     "year":2007,
     "value":1.97
    },
    {
     "year":2008,
     "value":1.97
    },
    {
     "year":2009,
     "value":1.97
    },
    {
     "year":2010,
     "value":1.97
    },
    {
     "year":2011,
     "value":1.97
    },
    {
     "year":2012,
     "value":1.98
    },
    {
     "year":2013,
     "value":1.98
    },
    {
     "year":2014,
     "value":1.98
    },
    {
     "year":2015,
     "value":1.99
    },
    {
     "year":2016,
     "value":2.0
    }
   ]
  },
  {
   "indicator":"prevalenceofcardiovasculardiseasesfemale_pcdfihme",
   "yearlyData":[
    {
     "year":1990,
     "value":3590.53
    },
    {
     "year":1991,
     "value":3604.99
    },
    {
     "year":1992,
     "value":3596.39
    },
    {
     "year":1993,
     "value":3592.21
    },
    {
     "year":1994,
     "value":3591.34
    },
    {
     "year":1995,
     "value":3596.13
    },
    {
     "year":1996,
     "value":3597.89
    },
    {
     "year":1997,
     "value":3601.86
    },
    {
     "year":1998,
     "value":3606.53
    },
    {
     "year":1999,
     "value":3612.31
    },
    {
     "year":2000,
     "value":3616.11
    },
    {
     "year":2001,
     "value":3640.21
    },
    {
     "year":2002,
     "value":3698.63
    },
    {
     "year":2003,
     "value":3772.15
    },
    {
     "year":2004,
     "value":3841.88
    },
    {
     "year":2005,
     "value":3883.03
    },
    {
     "year":2006,
     "value":3906.12
    },
    {
     "year":2007,
     "value":3927.27
    },
    {
     "year":2008,
     "value":3950.01
    },
    {
     "year":2009,
     "value":3970.73
    },
    {
     "year":2010,
     "value":3996.01
    },
    {
     "year":2011,
     "value":3999.68
    },
    {
     "year":2012,
     "value":3978.9
    },
    {
     "year":2013,
     "value":3947.42
    },
    {
     "year":2014,
     "value":3924.28
    },
    {
     "year":2015,
     "value":3934.66
    },
    {
     "year":2016,
     "value":3974.21
    },
    {
     "year":2017,
     "value":4016.31
    },
    {
     "year":2018,
     "value":4055.04
    },
    {
     "year":2019,
     "value":4093.89
    }
   ]
  },
  {
   "indicator":"prevalenceofcardiovasculardiseasesmale_pcdmihme",
   "yearlyData":[
    {
     "year":1990,
     "value":2940.33
    },
    {
     "year":1991,
     "value":2944.12
    },
    {
     "year":1992,
     "value":2933.38
    },
    {
     "year":1993,
     "value":2925.58
    },
    {
     "year":1994,
     "value":2921.05
    },
    {
     "year":1995,
     "value":2918.15
    },
    {
     "year":1996,
     "value":2918.03
    },
    {
     "year":1997,
     "value":2918.54
    },
    {
     "year":1998,
     "value":2920.54
    },
    {
     "year":1999,
     "value":2919.98
    },
    {
     "year":2000,
     "value":2920.36
    },
    {
     "year":2001,
     "value":2945.0
    },
    {
     "year":2002,
     "value":3005.74
    },
    {
     "year":2003,
     "value":3082.03
    },
    {
     "year":2004,
     "value":3149.95
    },
    {
     "year":2005,
     "value":3188.61
    },
    {
     "year":2006,
     "value":3207.63
    },
    {
     "year":2007,
     "value":3228.59
    },
    {
     "year":2008,
     "value":3246.37
    },
    {
     "year":2009,
     "value":3266.05
    },
    {
     "year":2010,
     "value":3286.72
    },
    {
     "year":2011,
     "value":3285.46
    },
    {
     "year":2012,
     "value":3251.2
    },
    {
     "year":2013,
     "value":3203.57
    },
    {
     "year":2014,
     "value":3165.65
    },
    {
     "year":2015,
     "value":3167.93
    },
    {
     "year":2016,
     "value":3204.69
    },
    {
     "year":2017,
     "value":3246.24
    },
    {
     "year":2018,
     "value":3285.0
    },
    {
     "year":2019,
     "value":3318.86
    }
   ]
  },
  {
   "indicator":"prevalenceofchronicrespiratorydiseasesfemale_pcrdfihme",
   "yearlyData":[
    {
     "year":1990,
     "value":5728.13
    },
    {
     "year":1991,
     "value":5718.96
    },
    {
     "year":1992,
     "value":5703.35
    },
    {
     "year":1993,
     "value":5694.51
    },
    {
     "year":1994,
     "value":5688.42
    },
    {
     "year":1995,
     "value":5684.56
    },
    {
     "year":1996,
     "value":5668.2
    },
    {
     "year":1997,
     "value":5625.19
    },
    {
     "year":1998,
     "value":5570.96
    },
    {
     "year":1999,
     "value":5514.69
    },
    {
     "year":2000,
     "value":5467.58
    },
    {
     "year":2001,
     "value":5420.46
    },
    {
     "year":2002,
     "value":5373.11
    },
    {
     "year":2003,
     "value":5328.88
    },
    {
     "year":2004,
     "value":5279.49
    },
    {
     "year":2005,
     "value":5230.44
    },
    {
     "year":2006,
     "value":5165.52
    },
    {
     "year":2007,
     "value":5087.83
    },
    {
     "year":2008,
     "value":5003.28
    },
    {
     "year":2009,
     "value":4935.56
    },
    {
     "year":2010,
     "value":4899.74
    },
    {
     "year":2011,
     "value":4881.23
    },
    {
     "year":2012,
     "value":4869.99
    },
    {
     "year":2013,
     "value":4866.92
    },
    {
     "year":2014,
     "value":4860.99
    },
    {
     "year":2015,
     "value":4857.54
    },
    {
     "year":2016,
     "value":4869.95
    },
    {
     "year":2017,
     "value":4894.49
    },
    {
     "year":2018,
     "value":4923.04
    },
    {
     "year":2019,
     "value":4956.21
    }
   ]
  },
  {
   "indicator":"prevalenceofchronicrespiratorydiseasesmale_pcrdmihme",
   "yearlyData":[
    {
     "year":1990,
     "value":6415.4
    },
    {
     "year":1991,
     "value":6396.16
    },
    {
     "year":1992,
     "value":6367.85
    },
    {
     "year":1993,
     "value":6343.3
    },
    {
     "year":1994,
     "value":6320.8
    },
    {
     "year":1995,
     "value":6295.84
    },
    {
     "year":1996,
     "value":6262.89
    },
    {
     "year":1997,
     "value":6213.55
    },
    {
     "year":1998,
     "value":6152.47
    },
    {
     "year":1999,
     "value":6094.66
    },
    {
     "year":2000,
     "value":6042.52
    },
    {
     "year":2001,
     "value":5989.28
    },
    {
     "year":2002,
     "value":5925.89
    },
    {
     "year":2003,
     "value":5855.82
    },
    {
     "year":2004,
     "value":5786.24
    },
    {
     "year":2005,
     "value":5723.93
    },
    {
     "year":2006,
     "value":5662.31
    },
    {
     "year":2007,
     "value":5589.05
    },
    {
     "year":2008,
     "value":5515.2
    },
    {
     "year":2009,
     "value":5453.12
    },
    {
     "year":2010,
     "value":5420.25
    },
    {
     "year":2011,
     "value":5405.98
    },
    {
     "year":2012,
     "value":5395.38
    },
    {
     "year":2013,
     "value":5391.17
    },
    {
     "year":2014,
     "value":5391.35
    },
    {
     "year":2015,
     "value":5387.82
    },
    {
     "year":2016,
     "value":5409.3
    },
    {
     "year":2017,
     "value":5449.49
    },
    {
     "year":2018,
     "value":5484.91
    },
    {
     "year":2019,
     "value":5537.83
    }
   ]
  },
  {
   "indicator":"prevalenceofdigestivediseasesfemale_pddfihme",
   "yearlyData":[
    {
     "year":1990,
     "value":20407.0
    },
    {
     "year":1991,
     "value":20387.9
    },
    {
     "year":1992,
     "value":20324.42
    },
    {
     "year":1993,
     "value":20249.89
    },
    {
     "year":1994,
     "value":20186.32
    },
    {
     "year":1995,
     "value":20126.86
    },
    {
     "year":1996,
     "value":20049.29
    },
    {
     "year":1997,
     "value":19955.18
    },
    {
     "year":1998,
     "value":19870.36
    },
    {
     "year":1999,
     "value":19801.23
    },
    {
     "year":2000,
     "value":19770.89
    },
    {
     "year":2001,
     "value":19723.82
    },
    {
     "year":2002,
     "value":19633.61
    },
    {
     "year":2003,
     "value":19550.74
    },
    {
     "year":2004,
     "value":19503.92
    },
    {
     "year":2005,
     "value":19528.1
    },
    {
     "year":2006,
     "value":19525.36
    },
    {
     "year":2007,
     "value":19425.99
    },
    {
     "year":2008,
     "value":19288.51
    },
    {
     "year":2009,
     "value":19196.59
    },
    {
     "year":2010,
     "value":19219.13
    },
    {
     "year":2011,
     "value":19271.43
    },
    {
     "year":2012,
     "value":19236.55
    },
    {
     "year":2013,
     "value":19174.62
    },
    {
     "year":2014,
     "value":19149.58
    },
    {
     "year":2015,
     "value":19227.85
    },
    {
     "year":2016,
     "value":19052.47
    },
    {
     "year":2017,
     "value":18881.34
    },
    {
     "year":2018,
     "value":19069.38
    },
    {
     "year":2019,
     "value":19265.2
    }
   ]
  },
  {
   "indicator":"prevalenceofdigestivediseasesmale_pddmihme",
   "yearlyData":[
    {
     "year":1990,
     "value":21445.93
    },
    {
     "year":1991,
     "value":21468.84
    },
    {
     "year":1992,
     "value":21453.52
    },
    {
     "year":1993,
     "value":21455.77
    },
    {
     "year":1994,
     "value":21446.34
    },
    {
     "year":1995,
     "value":21447.52
    },
    {
     "year":1996,
     "value":21455.58
    },
    {
     "year":1997,
     "value":21471.83
    },
    {
     "year":1998,
     "value":21490.27
    },
    {
     "year":1999,
     "value":21489.37
    },
    {
     "year":2000,
     "value":21471.71
    },
    {
     "year":2001,
     "value":21382.91
    },
    {
     "year":2002,
     "value":21193.32
    },
    {
     "year":2003,
     "value":20986.53
    },
    {
     "year":2004,
     "value":20838.53
    },
    {
     "year":2005,
     "value":20816.72
    },
    {
     "year":2006,
     "value":20806.72
    },
    {
     "year":2007,
     "value":20699.24
    },
    {
     "year":2008,
     "value":20565.51
    },
    {
     "year":2009,
     "value":20480.16
    },
    {
     "year":2010,
     "value":20528.6
    },
    {
     "year":2011,
     "value":20598.61
    },
    {
     "year":2012,
     "value":20589.96
    },
    {
     "year":2013,
     "value":20558.25
    },
    {
     "year":2014,
     "value":20572.99
    },
    {
     "year":2015,
     "value":20704.0
    },
    {
     "year":2016,
     "value":20519.1
    },
    {
     "year":2017,
     "value":20333.7
    },
    {
     "year":2018,
     "value":20532.8
    },
    {
     "year":2019,
     "value":20707.13
    }
   ]
  },
  {
   "indicator":"prevalenceofneurologicaldisordersfemale_pdnfihme",
   "yearlyData":[
    {
     "year":1990,
     "value":20768.29
    },
    {
     "year":1991,
     "value":20818.41
    },
    {
     "year":1992,
     "value":20858.0
    },
    {
     "year":1993,
     "value":20893.18
    },
    {
     "year":1994,
     "value":20923.19
    },
    {
     "year":1995,
     "value":20951.44
    },
    {
     "year":1996,
     "value":20989.09
    },
    {
     "year":1997,
     "value":21040.6
    },
    {
     "year":1998,
     "value":21098.34
    },
    {
     "year":1999,
     "value":21127.12
    },
    {
     "year":2000,
     "value":21142.38
    },
    {
     "year":2001,
     "value":21183.65
    },
    {
     "year":2002,
     "value":21247.35
    },
    {
     "year":2003,
     "value":21325.21
    },
    {
     "year":2004,
     "value":21408.48
    },
    {
     "year":2005,
     "value":21493.41
    },
    {
     "year":2006,
     "value":21580.09
    },
    {
     "year":2007,
     "value":21672.42
    },
    {
     "year":2008,
     "value":21762.38
    },
    {
     "year":2009,
     "value":21863.15
    },
    {
     "year":2010,
     "value":21964.41
    },
    {
     "year":2011,
     "value":22080.61
    },
    {
     "year":2012,
     "value":22192.9
    },
    {
     "year":2013,
     "value":22308.88
    },
    {
     "year":2014,
     "value":22418.06
    },
    {
     "year":2015,
     "value":22536.49
    },
    {
     "year":2016,
     "value":22659.12
    },
    {
     "year":2017,
     "value":22787.3
    },
    {
     "year":2018,
     "value":22908.53
    },
    {
     "year":2019,
     "value":23010.45
    }
   ]
  },
  {
   "indicator":"prevalenceofnoncommunicablediseasesfemale_poncdfihme",
   "yearlyData":[
    {
     "year":1990,
     "value":79887.93
    },
    {
     "year":1991,
     "value":79889.88
    },
    {
     "year":1992,
     "value":79864.48
    },
    {
     "year":1993,
     "value":79856.82
    },
    {
     "year":1994,
     "value":79856.65
    },
    {
     "year":1995,
     "value":79873.58
    },
    {
     "year":1996,
     "value":79871.17
    },
    {
     "year":1997,
     "value":79865.58
    },
    {
     "year":1998,
     "value":79867.59
    },
    {
     "year":1999,
     "value":79874.43
    },
    {
     "year":2000,
     "value":79883.48
    },
    {
     "year":2001,
     "value":79905.11
    },
    {
     "year":2002,
     "value":79928.4
    },
    {
     "year":2003,
     "value":79985.06
    },
    {
     "year":2004,
     "value":80042.57
    },
    {
     "year":2005,
     "value":80090.09
    },
    {
     "year":2006,
     "value":80148.64
    },
    {
     "year":2007,
     "value":80234.47
    },
    {
     "year":2008,
     "value":80336.12
    },
    {
     "year":2009,
     "value":80430.65
    },
    {
     "year":2010,
     "value":80525.49
    },
    {
     "year":2011,
     "value":80626.67
    },
    {
     "year":2012,
     "value":80724.97
    },
    {
     "year":2013,
     "value":80813.28
    },
    {
     "year":2014,
     "value":80869.92
    },
    {
     "year":2015,
     "value":80882.42
    },
    {
     "year":2016,
     "value":80760.23
    },
    {
     "year":2017,
     "value":80700.09
    },
    {
     "year":2018,
     "value":80808.82
    },
    {
     "year":2019,
     "value":80899.5
    }
   ]
  },
  {
   "indicator":"prevalenceofnoncommunicablediseasesmale_poncdmihme",
   "yearlyData":[
    {
     "year":1990,
     "value":57834.55
    },
    {
     "year":1991,
     "value":57814.59
    },
    {
     "year":1992,
     "value":57770.95
    },
    {
     "year":1993,
     "value":57782.33
    },
    {
     "year":1994,
     "value":57815.71
    },
    {
     "year":1995,
     "value":57846.94
    },
    {
     "year":1996,
     "value":57890.03
    },
    {
     "year":1997,
     "value":57938.43
    },
    {
     "year":1998,
     "value":57991.02
    },
    {
     "year":1999,
     "value":58035.95
    },
    {
     "year":2000,
     "value":58074.89
    },
    {
     "year":2001,
     "value":58085.25
    },
    {
     "year":2002,
     "value":58072.47
    },
    {
     "year":2003,
     "value":58068.06
    },
    {
     "year":2004,
     "value":58077.72
    },
    {
     "year":2005,
     "value":58094.89
    },
    {
     "year":2006,
     "value":58133.52
    },
    {
     "year":2007,
     "value":58185.46
    },
    {
     "year":2008,
     "value":58259.56
    },
    {
     "year":2009,
     "value":58318.95
    },
    {
     "year":2010,
     "value":58379.52
    },
    {
     "year":2011,
     "value":58420.9
    },
    {
     "year":2012,
     "value":58437.75
    },
    {
     "year":2013,
     "value":58418.38
    },
    {
     "year":2014,
     "value":58363.64
    },
    {
     "year":2015,
     "value":58260.37
    },
    {
     "year":2016,
     "value":58026.87
    },
    {
     "year":2017,
     "value":57916.08
    },
    {
     "year":2018,
     "value":58091.78
    },
    {
     "year":2019,
     "value":58448.2
    }
   ]
  },
  {
   "indicator":"psychologistworkinginmentalhealthsector_psycholmhs",
   "yearlyData":[
    {
     "year":2016,
     "value":0.08
    }
   ]
  },
  {
   "indicator":"publichealthriskcommunication_phrcomm",
   "yearlyData":[
    {
     "year":2018,
     "value":40.0
    },
    {
     "year":2019,
     "value":80.0
    },
    {
     "year":2020,
     "value":80.0
    }
   ]
  },
  {
   "indicator":"sexworkerspopulationsizeestimate_swpse",
   "yearlyData":[
    {
     "year":2013,
     "value":1600.0
    }
   ]
  },
  {
   "indicator":"suiciderateagestanderdized_srppas",
   "yearlyData":[
    {
     "year":2000,
     "value":23.41
    },
    {
     "year":2001,
     "value":22.48
    },
    {
     "year":2002,
     "value":22.07
    },
    {
     "year":2003,
     "value":20.74
    },
    {
     "year":2004,
     "value":20.88
    },
    {
     "year":2005,
     "value":20.95
    },
    {
     "year":2006,
     "value":21.16
    },
    {
     "year":2007,
     "value":20.83
    },
    {
     "year":2008,
     "value":21.27
    },
    {
     "year":2009,
     "value":20.86
    },
    {
     "year":2010,
     "value":20.53
    },
    {
     "year":2011,
     "value":20.16
    },
    {
     "year":2012,
     "value":19.73
    },
    {
     "year":2013,
     "value":19.24
    },
    {
     "year":2014,
     "value":18.87
    },
    {
     "year":2015,
     "value":18.69
    },
    {
     "year":2016,
     "value":18.3
    },
    {
     "year":2017,
     "value":18.0
    },
    {
     "year":2018,
     "value":17.84
    },
    {
     "year":2019,
     "value":17.26
    }
   ]
  },
  {
   "indicator":"surveillancecapacity_survcap",
   "yearlyData":[
    {
     "year":2018,
     "value":50.0
    },
    {
     "year":2019,
     "value":50.0
    },
    {
     "year":2020,
     "value":70.0
    }
   ]
  },
  {
   "indicator":"totalworkforceinmentalhealthsector_mhstotwf",
   "yearlyData":[
    {
     "year":2016,
     "value":2.29
    }
   ]
  }
 ]
}