{
 "Alpha-3 code":"TON",
 "Country or Area":"Tonga",
 "Latitude (average)":-20.0,
 "Longitude (average)":-175.0,
 "Group 1":"Oceania",
 "Group 2":"Polynesia",
 "LDC":false,
 "LLDC":false,
 "SIDS":true,
 "Income group":"Upper middle income",
 "UNDP_Region":"UNDP_AP",
 "indicators":[
  {
   "indicator":"ambientparticulatematterpollutionexposure_apmattpe",
   "yearlyData":[
    {
     "year":1990,
     "value":10.64
    },
    {
     "year":1995,
     "value":10.77
    },
    {
     "year":2000,
     "value":10.9
    },
    {
     "year":2005,
     "value":10.91
    },
    {
     "year":2010,
     "value":10.89
    },
    {
     "year":2011,
     "value":10.6
    },
    {
     "year":2012,
     "value":10.65
    },
    {
     "year":2013,
     "value":10.65
    },
    {
     "year":2014,
     "value":10.69
    },
    {
     "year":2015,
     "value":10.41
    },
    {
     "year":2016,
     "value":10.72
    },
    {
     "year":2017,
     "value":10.72
    },
    {
     "year":2018,
     "value":10.61
    },
    {
     "year":2019,
     "value":10.59
    }
   ]
  },
  {
   "indicator":"bedsformentalhealthingeneralhospital_bedsmhgh",
   "yearlyData":[
    {
     "year":2016,
     "value":24.44
    }
   ]
  },
  {
   "indicator":"changeinabsolutenumberofpeopleexposedtocoastalfloods_informcc",
   "yearlyData":[
    {
     "year":2050,
     "value":0.0
    }
   ]
  },
  {
   "indicator":"changeinabsolutenumberofpeopleexposedtodrought_informcc",
   "yearlyData":[
    {
     "year":2050,
     "value":0.0
    }
   ]
  },
  {
   "indicator":"changeinabsolutenumberofpeopleexposedtofloods_informcc",
   "yearlyData":[
    {
     "year":2050,
     "value":0.0
    }
   ]
  },
  {
   "indicator":"changeinabsolutenumberofpeopleexposedtomalariaanddengue_informcc",
   "yearlyData":[
    {
     "year":2050,
     "value":-1394.55
    }
   ]
  },
  {
   "indicator":"changeinhumanhazardandexposuretoconflict_informcc",
   "yearlyData":[
    {
     "year":2050,
     "value":0.0
    }
   ]
  },
  {
   "indicator":"chemicalevents_chemevents",
   "yearlyData":[
    {
     "year":2018,
     "value":0.0
    },
    {
     "year":2020,
     "value":0.0
    }
   ]
  },
  {
   "indicator":"coverageofprotectedareasinrelationtomarineareas_ermrmmpa",
   "yearlyData":[
    {
     "year":2000,
     "value":9.49
    },
    {
     "year":2001,
     "value":19.17
    },
    {
     "year":2002,
     "value":19.17
    },
    {
     "year":2003,
     "value":19.17
    },
    {
     "year":2004,
     "value":19.17
    },
    {
     "year":2005,
     "value":19.17
    },
    {
     "year":2006,
     "value":19.17
    },
    {
     "year":2007,
     "value":19.17
    },
    {
     "year":2008,
     "value":19.17
    },
    {
     "year":2009,
     "value":19.17
    },
    {
     "year":2010,
     "value":19.17
    },
    {
     "year":2011,
     "value":19.17
    },
    {
     "year":2012,
     "value":19.17
    },
    {
     "year":2013,
     "value":19.17
    },
    {
     "year":2014,
     "value":19.17
    },
    {
     "year":2015,
     "value":19.17
    },
    {
     "year":2016,
     "value":19.17
    },
    {
     "year":2017,
     "value":19.17
    },
    {
     "year":2018,
     "value":19.17
    },
    {
     "year":2019,
     "value":19.17
    },
    {
     "year":2020,
     "value":19.17
    },
    {
     "year":2021,
     "value":19.17
    },
    {
     "year":2022,
     "value":19.17
    }
   ]
  },
  {
   "indicator":"deathsattributedtocardiovasculardiseasesfemale_dcdfihme",
   "yearlyData":[
    {
     "year":1990,
     "value":97.02
    },
    {
     "year":1991,
     "value":98.19
    },
    {
     "year":1992,
     "value":97.05
    },
    {
     "year":1993,
     "value":99.88
    },
    {
     "year":1994,
     "value":102.55
    },
    {
     "year":1995,
     "value":102.53
    },
    {
     "year":1996,
     "value":104.09
    },
    {
     "year":1997,
     "value":109.21
    },
    {
     "year":1998,
     "value":114.78
    },
    {
     "year":1999,
     "value":115.6
    },
    {
     "year":2000,
     "value":114.14
    },
    {
     "year":2001,
     "value":114.36
    },
    {
     "year":2002,
     "value":112.98
    },
    {
     "year":2003,
     "value":111.45
    },
    {
     "year":2004,
     "value":110.26
    },
    {
     "year":2005,
     "value":112.14
    },
    {
     "year":2006,
     "value":114.68
    },
    {
     "year":2007,
     "value":118.85
    },
    {
     "year":2008,
     "value":122.98
    },
    {
     "year":2009,
     "value":126.69
    },
    {
     "year":2010,
     "value":130.03
    },
    {
     "year":2011,
     "value":132.72
    },
    {
     "year":2012,
     "value":135.2
    },
    {
     "year":2013,
     "value":138.06
    },
    {
     "year":2014,
     "value":140.88
    },
    {
     "year":2015,
     "value":143.13
    },
    {
     "year":2016,
     "value":145.08
    },
    {
     "year":2017,
     "value":146.93
    },
    {
     "year":2018,
     "value":148.48
    },
    {
     "year":2019,
     "value":149.89
    }
   ]
  },
  {
   "indicator":"deathsattributedtocardiovasculardiseasesmale_dcdmihme",
   "yearlyData":[
    {
     "year":1990,
     "value":148.87
    },
    {
     "year":1991,
     "value":150.53
    },
    {
     "year":1992,
     "value":151.99
    },
    {
     "year":1993,
     "value":155.73
    },
    {
     "year":1994,
     "value":158.55
    },
    {
     "year":1995,
     "value":157.48
    },
    {
     "year":1996,
     "value":160.66
    },
    {
     "year":1997,
     "value":166.34
    },
    {
     "year":1998,
     "value":179.17
    },
    {
     "year":1999,
     "value":193.91
    },
    {
     "year":2000,
     "value":194.2
    },
    {
     "year":2001,
     "value":189.2
    },
    {
     "year":2002,
     "value":192.0
    },
    {
     "year":2003,
     "value":194.45
    },
    {
     "year":2004,
     "value":187.54
    },
    {
     "year":2005,
     "value":172.34
    },
    {
     "year":2006,
     "value":173.58
    },
    {
     "year":2007,
     "value":176.57
    },
    {
     "year":2008,
     "value":179.43
    },
    {
     "year":2009,
     "value":181.85
    },
    {
     "year":2010,
     "value":183.94
    },
    {
     "year":2011,
     "value":185.51
    },
    {
     "year":2012,
     "value":187.1
    },
    {
     "year":2013,
     "value":189.41
    },
    {
     "year":2014,
     "value":191.44
    },
    {
     "year":2015,
     "value":193.2
    },
    {
     "year":2016,
     "value":194.76
    },
    {
     "year":2017,
     "value":196.18
    },
    {
     "year":2018,
     "value":197.38
    },
    {
     "year":2019,
     "value":198.31
    }
   ]
  },
  {
   "indicator":"deathsattributedtochronicrespiratorydiseasesfemale_dcrdfihme",
   "yearlyData":[
    {
     "year":1990,
     "value":22.71
    },
    {
     "year":1991,
     "value":22.73
    },
    {
     "year":1992,
     "value":22.3
    },
    {
     "year":1993,
     "value":22.68
    },
    {
     "year":1994,
     "value":22.99
    },
    {
     "year":1995,
     "value":22.82
    },
    {
     "year":1996,
     "value":23.0
    },
    {
     "year":1997,
     "value":23.82
    },
    {
     "year":1998,
     "value":24.6
    },
    {
     "year":1999,
     "value":24.62
    },
    {
     "year":2000,
     "value":24.2
    },
    {
     "year":2001,
     "value":24.08
    },
    {
     "year":2002,
     "value":23.65
    },
    {
     "year":2003,
     "value":23.12
    },
    {
     "year":2004,
     "value":22.64
    },
    {
     "year":2005,
     "value":22.74
    },
    {
     "year":2006,
     "value":22.95
    },
    {
     "year":2007,
     "value":23.44
    },
    {
     "year":2008,
     "value":23.9
    },
    {
     "year":2009,
     "value":24.28
    },
    {
     "year":2010,
     "value":24.61
    },
    {
     "year":2011,
     "value":24.77
    },
    {
     "year":2012,
     "value":25.04
    },
    {
     "year":2013,
     "value":25.36
    },
    {
     "year":2014,
     "value":25.64
    },
    {
     "year":2015,
     "value":25.84
    },
    {
     "year":2016,
     "value":26.02
    },
    {
     "year":2017,
     "value":26.25
    },
    {
     "year":2018,
     "value":26.41
    },
    {
     "year":2019,
     "value":26.56
    }
   ]
  },
  {
   "indicator":"deathsattributedtochronicrespiratorydiseasesmale_dcrdmihme",
   "yearlyData":[
    {
     "year":1990,
     "value":52.41
    },
    {
     "year":1991,
     "value":52.86
    },
    {
     "year":1992,
     "value":53.38
    },
    {
     "year":1993,
     "value":54.71
    },
    {
     "year":1994,
     "value":55.49
    },
    {
     "year":1995,
     "value":54.55
    },
    {
     "year":1996,
     "value":55.76
    },
    {
     "year":1997,
     "value":57.91
    },
    {
     "year":1998,
     "value":62.07
    },
    {
     "year":1999,
     "value":66.22
    },
    {
     "year":2000,
     "value":65.52
    },
    {
     "year":2001,
     "value":63.17
    },
    {
     "year":2002,
     "value":63.29
    },
    {
     "year":2003,
     "value":63.24
    },
    {
     "year":2004,
     "value":60.04
    },
    {
     "year":2005,
     "value":54.0
    },
    {
     "year":2006,
     "value":53.91
    },
    {
     "year":2007,
     "value":54.41
    },
    {
     "year":2008,
     "value":54.87
    },
    {
     "year":2009,
     "value":55.17
    },
    {
     "year":2010,
     "value":55.32
    },
    {
     "year":2011,
     "value":55.24
    },
    {
     "year":2012,
     "value":55.34
    },
    {
     "year":2013,
     "value":55.67
    },
    {
     "year":2014,
     "value":55.86
    },
    {
     "year":2015,
     "value":55.97
    },
    {
     "year":2016,
     "value":55.94
    },
    {
     "year":2017,
     "value":55.91
    },
    {
     "year":2018,
     "value":55.77
    },
    {
     "year":2019,
     "value":55.59
    }
   ]
  },
  {
   "indicator":"deathsattributedtodigestivediseasesfemale_dddfihme",
   "yearlyData":[
    {
     "year":1990,
     "value":25.59
    },
    {
     "year":1991,
     "value":25.55
    },
    {
     "year":1992,
     "value":25.21
    },
    {
     "year":1993,
     "value":25.61
    },
    {
     "year":1994,
     "value":25.82
    },
    {
     "year":1995,
     "value":25.61
    },
    {
     "year":1996,
     "value":25.63
    },
    {
     "year":1997,
     "value":26.12
    },
    {
     "year":1998,
     "value":26.76
    },
    {
     "year":1999,
     "value":26.67
    },
    {
     "year":2000,
     "value":26.14
    },
    {
     "year":2001,
     "value":25.63
    },
    {
     "year":2002,
     "value":25.06
    },
    {
     "year":2003,
     "value":24.42
    },
    {
     "year":2004,
     "value":23.77
    },
    {
     "year":2005,
     "value":23.79
    },
    {
     "year":2006,
     "value":23.88
    },
    {
     "year":2007,
     "value":24.22
    },
    {
     "year":2008,
     "value":24.42
    },
    {
     "year":2009,
     "value":24.59
    },
    {
     "year":2010,
     "value":24.85
    },
    {
     "year":2011,
     "value":25.0
    },
    {
     "year":2012,
     "value":25.17
    },
    {
     "year":2013,
     "value":25.37
    },
    {
     "year":2014,
     "value":25.47
    },
    {
     "year":2015,
     "value":25.57
    },
    {
     "year":2016,
     "value":25.77
    },
    {
     "year":2017,
     "value":26.11
    },
    {
     "year":2018,
     "value":26.41
    },
    {
     "year":2019,
     "value":26.72
    }
   ]
  },
  {
   "indicator":"deathsattributedtodigestivediseasesmale_dddmihme",
   "yearlyData":[
    {
     "year":1990,
     "value":44.7
    },
    {
     "year":1991,
     "value":44.66
    },
    {
     "year":1992,
     "value":44.82
    },
    {
     "year":1993,
     "value":45.27
    },
    {
     "year":1994,
     "value":45.59
    },
    {
     "year":1995,
     "value":45.3
    },
    {
     "year":1996,
     "value":45.55
    },
    {
     "year":1997,
     "value":46.03
    },
    {
     "year":1998,
     "value":47.9
    },
    {
     "year":1999,
     "value":50.01
    },
    {
     "year":2000,
     "value":49.72
    },
    {
     "year":2001,
     "value":48.49
    },
    {
     "year":2002,
     "value":48.55
    },
    {
     "year":2003,
     "value":48.73
    },
    {
     "year":2004,
     "value":47.41
    },
    {
     "year":2005,
     "value":44.06
    },
    {
     "year":2006,
     "value":44.04
    },
    {
     "year":2007,
     "value":44.31
    },
    {
     "year":2008,
     "value":44.4
    },
    {
     "year":2009,
     "value":44.42
    },
    {
     "year":2010,
     "value":44.57
    },
    {
     "year":2011,
     "value":44.61
    },
    {
     "year":2012,
     "value":44.68
    },
    {
     "year":2013,
     "value":44.81
    },
    {
     "year":2014,
     "value":44.82
    },
    {
     "year":2015,
     "value":44.84
    },
    {
     "year":2016,
     "value":44.93
    },
    {
     "year":2017,
     "value":45.18
    },
    {
     "year":2018,
     "value":45.4
    },
    {
     "year":2019,
     "value":45.61
    }
   ]
  },
  {
   "indicator":"deathsattributedtoneurologicaldisordersfemale_dndfihme",
   "yearlyData":[
    {
     "year":1990,
     "value":15.06
    },
    {
     "year":1991,
     "value":15.51
    },
    {
     "year":1992,
     "value":15.78
    },
    {
     "year":1993,
     "value":16.38
    },
    {
     "year":1994,
     "value":16.96
    },
    {
     "year":1995,
     "value":17.3
    },
    {
     "year":1996,
     "value":17.8
    },
    {
     "year":1997,
     "value":18.63
    },
    {
     "year":1998,
     "value":19.44
    },
    {
     "year":1999,
     "value":19.83
    },
    {
     "year":2000,
     "value":20.02
    },
    {
     "year":2001,
     "value":20.35
    },
    {
     "year":2002,
     "value":20.57
    },
    {
     "year":2003,
     "value":20.81
    },
    {
     "year":2004,
     "value":21.05
    },
    {
     "year":2005,
     "value":21.61
    },
    {
     "year":2006,
     "value":22.26
    },
    {
     "year":2007,
     "value":22.99
    },
    {
     "year":2008,
     "value":23.71
    },
    {
     "year":2009,
     "value":24.36
    },
    {
     "year":2010,
     "value":25.03
    },
    {
     "year":2011,
     "value":25.66
    },
    {
     "year":2012,
     "value":26.32
    },
    {
     "year":2013,
     "value":26.91
    },
    {
     "year":2014,
     "value":27.49
    },
    {
     "year":2015,
     "value":28.06
    },
    {
     "year":2016,
     "value":28.56
    },
    {
     "year":2017,
     "value":29.08
    },
    {
     "year":2018,
     "value":29.63
    },
    {
     "year":2019,
     "value":30.16
    }
   ]
  },
  {
   "indicator":"deathsattributedtoneurologicaldisordersmale_dndmihme",
   "yearlyData":[
    {
     "year":1990,
     "value":11.63
    },
    {
     "year":1991,
     "value":11.94
    },
    {
     "year":1992,
     "value":12.24
    },
    {
     "year":1993,
     "value":12.68
    },
    {
     "year":1994,
     "value":13.02
    },
    {
     "year":1995,
     "value":13.15
    },
    {
     "year":1996,
     "value":13.57
    },
    {
     "year":1997,
     "value":14.15
    },
    {
     "year":1998,
     "value":14.94
    },
    {
     "year":1999,
     "value":15.69
    },
    {
     "year":2000,
     "value":15.71
    },
    {
     "year":2001,
     "value":15.44
    },
    {
     "year":2002,
     "value":15.57
    },
    {
     "year":2003,
     "value":15.7
    },
    {
     "year":2004,
     "value":15.4
    },
    {
     "year":2005,
     "value":14.81
    },
    {
     "year":2006,
     "value":15.04
    },
    {
     "year":2007,
     "value":15.33
    },
    {
     "year":2008,
     "value":15.61
    },
    {
     "year":2009,
     "value":15.87
    },
    {
     "year":2010,
     "value":16.16
    },
    {
     "year":2011,
     "value":16.46
    },
    {
     "year":2012,
     "value":16.79
    },
    {
     "year":2013,
     "value":17.1
    },
    {
     "year":2014,
     "value":17.39
    },
    {
     "year":2015,
     "value":17.69
    },
    {
     "year":2016,
     "value":17.95
    },
    {
     "year":2017,
     "value":18.21
    },
    {
     "year":2018,
     "value":18.47
    },
    {
     "year":2019,
     "value":18.71
    }
   ]
  },
  {
   "indicator":"deathsattributedtononcommunicablediseasesfemale_doncdfihme",
   "yearlyData":[
    {
     "year":1990,
     "value":6.44
    },
    {
     "year":1991,
     "value":6.51
    },
    {
     "year":1992,
     "value":6.59
    },
    {
     "year":1993,
     "value":6.85
    },
    {
     "year":1994,
     "value":7.07
    },
    {
     "year":1995,
     "value":7.18
    },
    {
     "year":1996,
     "value":7.31
    },
    {
     "year":1997,
     "value":7.57
    },
    {
     "year":1998,
     "value":7.8
    },
    {
     "year":1999,
     "value":8.17
    },
    {
     "year":2000,
     "value":8.2
    },
    {
     "year":2001,
     "value":8.19
    },
    {
     "year":2002,
     "value":8.22
    },
    {
     "year":2003,
     "value":8.28
    },
    {
     "year":2004,
     "value":8.29
    },
    {
     "year":2005,
     "value":8.07
    },
    {
     "year":2006,
     "value":7.9
    },
    {
     "year":2007,
     "value":7.66
    },
    {
     "year":2008,
     "value":7.44
    },
    {
     "year":2009,
     "value":7.2
    },
    {
     "year":2010,
     "value":7.04
    },
    {
     "year":2011,
     "value":6.87
    },
    {
     "year":2012,
     "value":6.75
    },
    {
     "year":2013,
     "value":6.67
    },
    {
     "year":2014,
     "value":6.63
    },
    {
     "year":2015,
     "value":6.63
    },
    {
     "year":2016,
     "value":6.63
    },
    {
     "year":2017,
     "value":6.63
    },
    {
     "year":2018,
     "value":6.63
    },
    {
     "year":2019,
     "value":6.65
    }
   ]
  },
  {
   "indicator":"deathsattributedtononcommunicablediseasesmale_doncdmihme",
   "yearlyData":[
    {
     "year":1990,
     "value":15.62
    },
    {
     "year":1991,
     "value":15.6
    },
    {
     "year":1992,
     "value":15.58
    },
    {
     "year":1993,
     "value":15.88
    },
    {
     "year":1994,
     "value":16.07
    },
    {
     "year":1995,
     "value":16.05
    },
    {
     "year":1996,
     "value":16.2
    },
    {
     "year":1997,
     "value":16.53
    },
    {
     "year":1998,
     "value":17.11
    },
    {
     "year":1999,
     "value":18.13
    },
    {
     "year":2000,
     "value":18.11
    },
    {
     "year":2001,
     "value":17.81
    },
    {
     "year":2002,
     "value":17.86
    },
    {
     "year":2003,
     "value":17.97
    },
    {
     "year":2004,
     "value":17.63
    },
    {
     "year":2005,
     "value":16.78
    },
    {
     "year":2006,
     "value":16.79
    },
    {
     "year":2007,
     "value":16.74
    },
    {
     "year":2008,
     "value":16.69
    },
    {
     "year":2009,
     "value":16.48
    },
    {
     "year":2010,
     "value":16.33
    },
    {
     "year":2011,
     "value":16.12
    },
    {
     "year":2012,
     "value":15.94
    },
    {
     "year":2013,
     "value":15.79
    },
    {
     "year":2014,
     "value":15.66
    },
    {
     "year":2015,
     "value":15.56
    },
    {
     "year":2016,
     "value":15.42
    },
    {
     "year":2017,
     "value":15.23
    },
    {
     "year":2018,
     "value":15.09
    },
    {
     "year":2019,
     "value":14.96
    }
   ]
  },
  {
   "indicator":"degreeofimplementationofinternationalinstrumentsaimingtocombatillegalunreportedunregulatedfishing_ilfish",
   "yearlyData":[
    {
     "year":2018,
     "value":3.0
    }
   ]
  },
  {
   "indicator":"forestareatothepercentageoflandarea_frstarea",
   "yearlyData":[
    {
     "year":1990,
     "value":12.43
    },
    {
     "year":1991,
     "value":12.43
    },
    {
     "year":1992,
     "value":12.43
    },
    {
     "year":1993,
     "value":12.43
    },
    {
     "year":1994,
     "value":12.43
    },
    {
     "year":1995,
     "value":12.43
    },
    {
     "year":1996,
     "value":12.43
    },
    {
     "year":1997,
     "value":12.43
    },
    {
     "year":1998,
     "value":12.43
    },
    {
     "year":1999,
     "value":12.43
    },
    {
     "year":2000,
     "value":12.43
    },
    {
     "year":2001,
     "value":12.43
    },
    {
     "year":2002,
     "value":12.43
    },
    {
     "year":2003,
     "value":12.43
    },
    {
     "year":2004,
     "value":12.43
    },
    {
     "year":2005,
     "value":12.43
    },
    {
     "year":2006,
     "value":12.43
    },
    {
     "year":2007,
     "value":12.43
    },
    {
     "year":2008,
     "value":12.43
    },
    {
     "year":2009,
     "value":12.43
    },
    {
     "year":2010,
     "value":12.43
    },
    {
     "year":2011,
     "value":12.43
    },
    {
     "year":2012,
     "value":12.43
    },
    {
     "year":2013,
     "value":12.43
    },
    {
     "year":2014,
     "value":12.43
    },
    {
     "year":2015,
     "value":12.43
    },
    {
     "year":2016,
     "value":12.43
    },
    {
     "year":2017,
     "value":12.43
    },
    {
     "year":2018,
     "value":12.43
    },
    {
     "year":2019,
     "value":12.43
    },
    {
     "year":2020,
     "value":12.43
    }
   ]
  },
  {
   "indicator":"gghedaspercentageofgge_gghedgge",
   "yearlyData":[
    {
     "year":2000,
     "value":11.41
    },
    {
     "year":2001,
     "value":12.74
    },
    {
     "year":2002,
     "value":12.14
    },
    {
     "year":2003,
     "value":12.09
    },
    {
     "year":2004,
     "value":12.74
    },
    {
     "year":2005,
     "value":13.11
    },
    {
     "year":2006,
     "value":11.16
    },
    {
     "year":2007,
     "value":13.68
    },
    {
     "year":2008,
     "value":12.08
    },
    {
     "year":2009,
     "value":12.72
    },
    {
     "year":2010,
     "value":10.07
    },
    {
     "year":2011,
     "value":8.4
    },
    {
     "year":2012,
     "value":8.69
    },
    {
     "year":2013,
     "value":8.11
    },
    {
     "year":2014,
     "value":9.18
    },
    {
     "year":2015,
     "value":7.38
    },
    {
     "year":2016,
     "value":8.03
    },
    {
     "year":2017,
     "value":7.32
    },
    {
     "year":2018,
     "value":8.07
    },
    {
     "year":2019,
     "value":7.51
    },
    {
     "year":2020,
     "value":7.88
    }
   ]
  },
  {
   "indicator":"governmentexpenditureontotaleducation_wdi",
   "yearlyData":[
    {
     "year":1984,
     "value":10.35
    },
    {
     "year":1998,
     "value":5.52
    },
    {
     "year":1999,
     "value":5.38
    },
    {
     "year":2000,
     "value":4.88
    },
    {
     "year":2001,
     "value":4.48
    },
    {
     "year":2002,
     "value":3.8
    },
    {
     "year":2003,
     "value":4.16
    },
    {
     "year":2004,
     "value":3.91
    },
    {
     "year":2018,
     "value":6.37
    },
    {
     "year":2019,
     "value":7.96
    },
    {
     "year":2020,
     "value":6.52
    },
    {
     "year":2021,
     "value":6.61
    }
   ]
  },
  {
   "indicator":"householdairpolutionfromsolidfuels_hapsfuel",
   "yearlyData":[
    {
     "year":1990,
     "value":0.67
    },
    {
     "year":1991,
     "value":0.66
    },
    {
     "year":1992,
     "value":0.65
    },
    {
     "year":1993,
     "value":0.63
    },
    {
     "year":1994,
     "value":0.62
    },
    {
     "year":1995,
     "value":0.6
    },
    {
     "year":1996,
     "value":0.58
    },
    {
     "year":1997,
     "value":0.57
    },
    {
     "year":1998,
     "value":0.55
    },
    {
     "year":1999,
     "value":0.54
    },
    {
     "year":2000,
     "value":0.52
    },
    {
     "year":2001,
     "value":0.51
    },
    {
     "year":2002,
     "value":0.5
    },
    {
     "year":2003,
     "value":0.48
    },
    {
     "year":2004,
     "value":0.47
    },
    {
     "year":2005,
     "value":0.46
    },
    {
     "year":2006,
     "value":0.46
    },
    {
     "year":2007,
     "value":0.46
    },
    {
     "year":2008,
     "value":0.46
    },
    {
     "year":2009,
     "value":0.46
    },
    {
     "year":2010,
     "value":0.46
    },
    {
     "year":2011,
     "value":0.45
    },
    {
     "year":2012,
     "value":0.45
    },
    {
     "year":2013,
     "value":0.44
    },
    {
     "year":2014,
     "value":0.43
    },
    {
     "year":2015,
     "value":0.42
    },
    {
     "year":2016,
     "value":0.41
    },
    {
     "year":2017,
     "value":0.39
    },
    {
     "year":2018,
     "value":0.38
    },
    {
     "year":2019,
     "value":0.36
    }
   ]
  },
  {
   "indicator":"medicalwastetonsperyear_medwaste",
   "yearlyData":[
    {
     "year":2014,
     "value":102.23
    }
   ]
  },
  {
   "indicator":"mentalhealthoutpatientfacilities_mhof",
   "yearlyData":[
    {
     "year":2016,
     "value":0.94
    }
   ]
  },
  {
   "indicator":"mentalhealthunitsingeneralhospitals_mhugh",
   "yearlyData":[
    {
     "year":2016,
     "value":0.94
    }
   ]
  },
  {
   "indicator":"mentalhealthunitsingeneralhospitalsadmissions_mhugha",
   "yearlyData":[
    {
     "year":2014,
     "value":199.46
    }
   ]
  },
  {
   "indicator":"numberofdeathsandmissingpersonsanddirectlyaffectedpeopleattributedtodisaster_ndmdsr",
   "yearlyData":[
    {
     "year":2005,
     "value":0.0
    },
    {
     "year":2006,
     "value":0.0
    },
    {
     "year":2007,
     "value":0.0
    },
    {
     "year":2008,
     "value":0.0
    },
    {
     "year":2009,
     "value":14.93
    },
    {
     "year":2011,
     "value":0.0
    },
    {
     "year":2012,
     "value":0.0
    },
    {
     "year":2013,
     "value":0.0
    },
    {
     "year":2014,
     "value":0.94
    },
    {
     "year":2015,
     "value":0.0
    },
    {
     "year":2016,
     "value":0.0
    },
    {
     "year":2017,
     "value":0.0
    },
    {
     "year":2018,
     "value":0.0
    },
    {
     "year":2019,
     "value":0.0
    },
    {
     "year":2020,
     "value":0.0
    }
   ]
  },
  {
   "indicator":"nursesworkinginmentalhealthsector_nursmhs",
   "yearlyData":[
    {
     "year":2016,
     "value":16.92
    }
   ]
  },
  {
   "indicator":"percentofterrestrialprotectedareasoftotallandareas_trrprotarea",
   "yearlyData":[
    {
     "year":2016,
     "value":15.92
    },
    {
     "year":2017,
     "value":15.91
    },
    {
     "year":2018,
     "value":15.91
    },
    {
     "year":2019,
     "value":12.59
    },
    {
     "year":2020,
     "value":12.59
    },
    {
     "year":2021,
     "value":12.59
    },
    {
     "year":2022,
     "value":12.59
    }
   ]
  },
  {
   "indicator":"prevalencealcoholandsubstanceusedisordersbothsexes_pasdis",
   "yearlyData":[
    {
     "year":1990,
     "value":1.52
    },
    {
     "year":1991,
     "value":1.52
    },
    {
     "year":1992,
     "value":1.52
    },
    {
     "year":1993,
     "value":1.52
    },
    {
     "year":1994,
     "value":1.53
    },
    {
     "year":1995,
     "value":1.53
    },
    {
     "year":1996,
     "value":1.53
    },
    {
     "year":1997,
     "value":1.54
    },
    {
     "year":1998,
     "value":1.54
    },
    {
     "year":1999,
     "value":1.54
    },
    {
     "year":2000,
     "value":1.55
    },
    {
     "year":2001,
     "value":1.54
    },
    {
     "year":2002,
     "value":1.55
    },
    {
     "year":2003,
     "value":1.55
    },
    {
     "year":2004,
     "value":1.55
    },
    {
     "year":2005,
     "value":1.55
    },
    {
     "year":2006,
     "value":1.55
    },
    {
     "year":2007,
     "value":1.55
    },
    {
     "year":2008,
     "value":1.55
    },
    {
     "year":2009,
     "value":1.55
    },
    {
     "year":2010,
     "value":1.55
    },
    {
     "year":2011,
     "value":1.56
    },
    {
     "year":2012,
     "value":1.56
    },
    {
     "year":2013,
     "value":1.56
    },
    {
     "year":2014,
     "value":1.57
    },
    {
     "year":2015,
     "value":1.57
    },
    {
     "year":2016,
     "value":1.57
    }
   ]
  },
  {
   "indicator":"prevalenceofcardiovasculardiseasesfemale_pcdfihme",
   "yearlyData":[
    {
     "year":1990,
     "value":4718.66
    },
    {
     "year":1991,
     "value":4776.58
    },
    {
     "year":1992,
     "value":4837.76
    },
    {
     "year":1993,
     "value":4902.56
    },
    {
     "year":1994,
     "value":4965.07
    },
    {
     "year":1995,
     "value":5025.56
    },
    {
     "year":1996,
     "value":5118.83
    },
    {
     "year":1997,
     "value":5247.53
    },
    {
     "year":1998,
     "value":5388.27
    },
    {
     "year":1999,
     "value":5504.57
    },
    {
     "year":2000,
     "value":5579.93
    },
    {
     "year":2001,
     "value":5622.85
    },
    {
     "year":2002,
     "value":5655.38
    },
    {
     "year":2003,
     "value":5688.65
    },
    {
     "year":2004,
     "value":5720.4
    },
    {
     "year":2005,
     "value":5755.59
    },
    {
     "year":2006,
     "value":5761.04
    },
    {
     "year":2007,
     "value":5733.53
    },
    {
     "year":2008,
     "value":5695.6
    },
    {
     "year":2009,
     "value":5668.82
    },
    {
     "year":2010,
     "value":5681.73
    },
    {
     "year":2011,
     "value":5725.03
    },
    {
     "year":2012,
     "value":5770.42
    },
    {
     "year":2013,
     "value":5821.22
    },
    {
     "year":2014,
     "value":5871.84
    },
    {
     "year":2015,
     "value":5931.05
    },
    {
     "year":2016,
     "value":6008.37
    },
    {
     "year":2017,
     "value":6087.89
    },
    {
     "year":2018,
     "value":6149.32
    },
    {
     "year":2019,
     "value":6207.45
    }
   ]
  },
  {
   "indicator":"prevalenceofcardiovasculardiseasesmale_pcdmihme",
   "yearlyData":[
    {
     "year":1990,
     "value":4273.76
    },
    {
     "year":1991,
     "value":4331.39
    },
    {
     "year":1992,
     "value":4391.66
    },
    {
     "year":1993,
     "value":4448.91
    },
    {
     "year":1994,
     "value":4504.68
    },
    {
     "year":1995,
     "value":4558.56
    },
    {
     "year":1996,
     "value":4641.25
    },
    {
     "year":1997,
     "value":4763.96
    },
    {
     "year":1998,
     "value":4887.62
    },
    {
     "year":1999,
     "value":4984.43
    },
    {
     "year":2000,
     "value":5029.47
    },
    {
     "year":2001,
     "value":5040.04
    },
    {
     "year":2002,
     "value":5045.14
    },
    {
     "year":2003,
     "value":5046.2
    },
    {
     "year":2004,
     "value":5050.03
    },
    {
     "year":2005,
     "value":5066.33
    },
    {
     "year":2006,
     "value":5065.23
    },
    {
     "year":2007,
     "value":5026.1
    },
    {
     "year":2008,
     "value":4974.51
    },
    {
     "year":2009,
     "value":4936.96
    },
    {
     "year":2010,
     "value":4942.51
    },
    {
     "year":2011,
     "value":4981.42
    },
    {
     "year":2012,
     "value":5021.68
    },
    {
     "year":2013,
     "value":5068.81
    },
    {
     "year":2014,
     "value":5117.14
    },
    {
     "year":2015,
     "value":5172.37
    },
    {
     "year":2016,
     "value":5239.95
    },
    {
     "year":2017,
     "value":5309.9
    },
    {
     "year":2018,
     "value":5369.21
    },
    {
     "year":2019,
     "value":5430.44
    }
   ]
  },
  {
   "indicator":"prevalenceofchronicrespiratorydiseasesfemale_pcrdfihme",
   "yearlyData":[
    {
     "year":1990,
     "value":4895.24
    },
    {
     "year":1991,
     "value":4786.59
    },
    {
     "year":1992,
     "value":4698.09
    },
    {
     "year":1993,
     "value":4627.47
    },
    {
     "year":1994,
     "value":4577.32
    },
    {
     "year":1995,
     "value":4553.71
    },
    {
     "year":1996,
     "value":4563.8
    },
    {
     "year":1997,
     "value":4603.48
    },
    {
     "year":1998,
     "value":4649.5
    },
    {
     "year":1999,
     "value":4682.39
    },
    {
     "year":2000,
     "value":4684.93
    },
    {
     "year":2001,
     "value":4661.3
    },
    {
     "year":2002,
     "value":4626.06
    },
    {
     "year":2003,
     "value":4587.4
    },
    {
     "year":2004,
     "value":4538.47
    },
    {
     "year":2005,
     "value":4490.65
    },
    {
     "year":2006,
     "value":4417.71
    },
    {
     "year":2007,
     "value":4311.88
    },
    {
     "year":2008,
     "value":4202.63
    },
    {
     "year":2009,
     "value":4109.08
    },
    {
     "year":2010,
     "value":4064.36
    },
    {
     "year":2011,
     "value":4050.87
    },
    {
     "year":2012,
     "value":4041.47
    },
    {
     "year":2013,
     "value":4037.03
    },
    {
     "year":2014,
     "value":4039.36
    },
    {
     "year":2015,
     "value":4048.9
    },
    {
     "year":2016,
     "value":4294.02
    },
    {
     "year":2017,
     "value":4533.53
    },
    {
     "year":2018,
     "value":4539.28
    },
    {
     "year":2019,
     "value":4497.0
    }
   ]
  },
  {
   "indicator":"prevalenceofchronicrespiratorydiseasesmale_pcrdmihme",
   "yearlyData":[
    {
     "year":1990,
     "value":5223.72
    },
    {
     "year":1991,
     "value":5100.72
    },
    {
     "year":1992,
     "value":5001.3
    },
    {
     "year":1993,
     "value":4924.78
    },
    {
     "year":1994,
     "value":4873.97
    },
    {
     "year":1995,
     "value":4851.75
    },
    {
     "year":1996,
     "value":4869.11
    },
    {
     "year":1997,
     "value":4919.63
    },
    {
     "year":1998,
     "value":4978.24
    },
    {
     "year":1999,
     "value":5017.63
    },
    {
     "year":2000,
     "value":5022.91
    },
    {
     "year":2001,
     "value":4996.01
    },
    {
     "year":2002,
     "value":4964.61
    },
    {
     "year":2003,
     "value":4923.6
    },
    {
     "year":2004,
     "value":4878.0
    },
    {
     "year":2005,
     "value":4834.04
    },
    {
     "year":2006,
     "value":4763.76
    },
    {
     "year":2007,
     "value":4649.96
    },
    {
     "year":2008,
     "value":4523.8
    },
    {
     "year":2009,
     "value":4418.65
    },
    {
     "year":2010,
     "value":4365.65
    },
    {
     "year":2011,
     "value":4352.73
    },
    {
     "year":2012,
     "value":4339.59
    },
    {
     "year":2013,
     "value":4331.85
    },
    {
     "year":2014,
     "value":4332.93
    },
    {
     "year":2015,
     "value":4339.24
    },
    {
     "year":2016,
     "value":4470.55
    },
    {
     "year":2017,
     "value":4605.18
    },
    {
     "year":2018,
     "value":4624.81
    },
    {
     "year":2019,
     "value":4626.38
    }
   ]
  },
  {
   "indicator":"prevalenceofdigestivediseasesfemale_pddfihme",
   "yearlyData":[
    {
     "year":1990,
     "value":23866.4
    },
    {
     "year":1991,
     "value":23993.07
    },
    {
     "year":1992,
     "value":24121.94
    },
    {
     "year":1993,
     "value":24285.11
    },
    {
     "year":1994,
     "value":24478.71
    },
    {
     "year":1995,
     "value":24733.43
    },
    {
     "year":1996,
     "value":24919.74
    },
    {
     "year":1997,
     "value":24964.96
    },
    {
     "year":1998,
     "value":24955.11
    },
    {
     "year":1999,
     "value":24963.38
    },
    {
     "year":2000,
     "value":25070.5
    },
    {
     "year":2001,
     "value":25183.21
    },
    {
     "year":2002,
     "value":25221.45
    },
    {
     "year":2003,
     "value":25222.29
    },
    {
     "year":2004,
     "value":25221.23
    },
    {
     "year":2005,
     "value":25271.62
    },
    {
     "year":2006,
     "value":25189.25
    },
    {
     "year":2007,
     "value":24894.56
    },
    {
     "year":2008,
     "value":24521.59
    },
    {
     "year":2009,
     "value":24217.26
    },
    {
     "year":2010,
     "value":24121.52
    },
    {
     "year":2011,
     "value":24147.32
    },
    {
     "year":2012,
     "value":24150.91
    },
    {
     "year":2013,
     "value":24154.18
    },
    {
     "year":2014,
     "value":24199.63
    },
    {
     "year":2015,
     "value":24320.84
    },
    {
     "year":2016,
     "value":24527.53
    },
    {
     "year":2017,
     "value":24742.13
    },
    {
     "year":2018,
     "value":24823.5
    },
    {
     "year":2019,
     "value":24768.11
    }
   ]
  },
  {
   "indicator":"prevalenceofdigestivediseasesmale_pddmihme",
   "yearlyData":[
    {
     "year":1990,
     "value":22759.64
    },
    {
     "year":1991,
     "value":22945.49
    },
    {
     "year":1992,
     "value":23113.02
    },
    {
     "year":1993,
     "value":23293.62
    },
    {
     "year":1994,
     "value":23499.14
    },
    {
     "year":1995,
     "value":23754.39
    },
    {
     "year":1996,
     "value":23916.29
    },
    {
     "year":1997,
     "value":23905.71
    },
    {
     "year":1998,
     "value":23823.53
    },
    {
     "year":1999,
     "value":23765.29
    },
    {
     "year":2000,
     "value":23835.22
    },
    {
     "year":2001,
     "value":23987.52
    },
    {
     "year":2002,
     "value":24104.66
    },
    {
     "year":2003,
     "value":24198.01
    },
    {
     "year":2004,
     "value":24277.42
    },
    {
     "year":2005,
     "value":24357.78
    },
    {
     "year":2006,
     "value":24281.85
    },
    {
     "year":2007,
     "value":23986.63
    },
    {
     "year":2008,
     "value":23604.02
    },
    {
     "year":2009,
     "value":23266.73
    },
    {
     "year":2010,
     "value":23114.91
    },
    {
     "year":2011,
     "value":23056.16
    },
    {
     "year":2012,
     "value":22933.34
    },
    {
     "year":2013,
     "value":22813.28
    },
    {
     "year":2014,
     "value":22755.45
    },
    {
     "year":2015,
     "value":22814.16
    },
    {
     "year":2016,
     "value":23064.93
    },
    {
     "year":2017,
     "value":23337.94
    },
    {
     "year":2018,
     "value":23410.32
    },
    {
     "year":2019,
     "value":23321.74
    }
   ]
  },
  {
   "indicator":"prevalenceofneurologicaldisordersfemale_pdnfihme",
   "yearlyData":[
    {
     "year":1990,
     "value":25672.05
    },
    {
     "year":1991,
     "value":25747.17
    },
    {
     "year":1992,
     "value":25816.77
    },
    {
     "year":1993,
     "value":25883.82
    },
    {
     "year":1994,
     "value":25957.86
    },
    {
     "year":1995,
     "value":26028.67
    },
    {
     "year":1996,
     "value":26092.58
    },
    {
     "year":1997,
     "value":26163.7
    },
    {
     "year":1998,
     "value":26230.32
    },
    {
     "year":1999,
     "value":26275.29
    },
    {
     "year":2000,
     "value":26318.23
    },
    {
     "year":2001,
     "value":26345.16
    },
    {
     "year":2002,
     "value":26369.31
    },
    {
     "year":2003,
     "value":26384.34
    },
    {
     "year":2004,
     "value":26392.94
    },
    {
     "year":2005,
     "value":26398.8
    },
    {
     "year":2006,
     "value":26400.45
    },
    {
     "year":2007,
     "value":26404.11
    },
    {
     "year":2008,
     "value":26403.66
    },
    {
     "year":2009,
     "value":26407.97
    },
    {
     "year":2010,
     "value":26417.38
    },
    {
     "year":2011,
     "value":26444.25
    },
    {
     "year":2012,
     "value":26480.79
    },
    {
     "year":2013,
     "value":26526.05
    },
    {
     "year":2014,
     "value":26586.56
    },
    {
     "year":2015,
     "value":26644.08
    },
    {
     "year":2016,
     "value":26710.25
    },
    {
     "year":2017,
     "value":26785.39
    },
    {
     "year":2018,
     "value":26856.78
    },
    {
     "year":2019,
     "value":26934.65
    }
   ]
  },
  {
   "indicator":"prevalenceofnoncommunicablediseasesfemale_poncdfihme",
   "yearlyData":[
    {
     "year":1990,
     "value":74970.52
    },
    {
     "year":1991,
     "value":74986.35
    },
    {
     "year":1992,
     "value":74992.26
    },
    {
     "year":1993,
     "value":75002.24
    },
    {
     "year":1994,
     "value":75024.85
    },
    {
     "year":1995,
     "value":75062.24
    },
    {
     "year":1996,
     "value":75115.87
    },
    {
     "year":1997,
     "value":75185.32
    },
    {
     "year":1998,
     "value":75258.32
    },
    {
     "year":1999,
     "value":75323.02
    },
    {
     "year":2000,
     "value":75368.39
    },
    {
     "year":2001,
     "value":75390.36
    },
    {
     "year":2002,
     "value":75396.58
    },
    {
     "year":2003,
     "value":75400.3
    },
    {
     "year":2004,
     "value":75405.73
    },
    {
     "year":2005,
     "value":75423.86
    },
    {
     "year":2006,
     "value":75453.05
    },
    {
     "year":2007,
     "value":75479.98
    },
    {
     "year":2008,
     "value":75512.61
    },
    {
     "year":2009,
     "value":75539.84
    },
    {
     "year":2010,
     "value":75570.11
    },
    {
     "year":2011,
     "value":75794.21
    },
    {
     "year":2012,
     "value":76256.58
    },
    {
     "year":2013,
     "value":76793.53
    },
    {
     "year":2014,
     "value":77259.22
    },
    {
     "year":2015,
     "value":77477.24
    },
    {
     "year":2016,
     "value":77458.0
    },
    {
     "year":2017,
     "value":77432.85
    },
    {
     "year":2018,
     "value":77477.35
    },
    {
     "year":2019,
     "value":77502.4
    }
   ]
  },
  {
   "indicator":"prevalenceofnoncommunicablediseasesmale_poncdmihme",
   "yearlyData":[
    {
     "year":1990,
     "value":51817.26
    },
    {
     "year":1991,
     "value":51972.37
    },
    {
     "year":1992,
     "value":52090.46
    },
    {
     "year":1993,
     "value":52159.74
    },
    {
     "year":1994,
     "value":52201.97
    },
    {
     "year":1995,
     "value":52224.17
    },
    {
     "year":1996,
     "value":52174.66
    },
    {
     "year":1997,
     "value":52004.59
    },
    {
     "year":1998,
     "value":51797.55
    },
    {
     "year":1999,
     "value":51625.68
    },
    {
     "year":2000,
     "value":51545.97
    },
    {
     "year":2001,
     "value":51566.36
    },
    {
     "year":2002,
     "value":51609.96
    },
    {
     "year":2003,
     "value":51667.59
    },
    {
     "year":2004,
     "value":51738.77
    },
    {
     "year":2005,
     "value":51809.55
    },
    {
     "year":2006,
     "value":51915.17
    },
    {
     "year":2007,
     "value":52069.94
    },
    {
     "year":2008,
     "value":52231.44
    },
    {
     "year":2009,
     "value":52382.49
    },
    {
     "year":2010,
     "value":52484.71
    },
    {
     "year":2011,
     "value":52601.63
    },
    {
     "year":2012,
     "value":52742.34
    },
    {
     "year":2013,
     "value":52900.33
    },
    {
     "year":2014,
     "value":53022.14
    },
    {
     "year":2015,
     "value":53091.28
    },
    {
     "year":2016,
     "value":52768.63
    },
    {
     "year":2017,
     "value":52384.06
    },
    {
     "year":2018,
     "value":52283.79
    },
    {
     "year":2019,
     "value":52223.53
    }
   ]
  },
  {
   "indicator":"psychiatricsworkinginmentalhealthsector_psychiamhs",
   "yearlyData":[
    {
     "year":2016,
     "value":2.82
    }
   ]
  },
  {
   "indicator":"psychologistworkinginmentalhealthsector_psycholmhs",
   "yearlyData":[
    {
     "year":2016,
     "value":1.88
    }
   ]
  },
  {
   "indicator":"publichealthriskcommunication_phrcomm",
   "yearlyData":[
    {
     "year":2018,
     "value":80.0
    },
    {
     "year":2020,
     "value":80.0
    }
   ]
  },
  {
   "indicator":"sexworkerspopulationsizeestimate_swpse",
   "yearlyData":[
    {
     "year":2016,
     "value":1000.0
    }
   ]
  },
  {
   "indicator":"suiciderateagestanderdized_srppas",
   "yearlyData":[
    {
     "year":2000,
     "value":5.13
    },
    {
     "year":2001,
     "value":5.1
    },
    {
     "year":2002,
     "value":5.0
    },
    {
     "year":2003,
     "value":5.08
    },
    {
     "year":2004,
     "value":5.01
    },
    {
     "year":2005,
     "value":4.79
    },
    {
     "year":2006,
     "value":4.73
    },
    {
     "year":2007,
     "value":4.8
    },
    {
     "year":2008,
     "value":4.71
    },
    {
     "year":2009,
     "value":5.06
    },
    {
     "year":2010,
     "value":5.34
    },
    {
     "year":2011,
     "value":5.21
    },
    {
     "year":2012,
     "value":5.25
    },
    {
     "year":2013,
     "value":5.27
    },
    {
     "year":2014,
     "value":5.35
    },
    {
     "year":2015,
     "value":5.3
    },
    {
     "year":2016,
     "value":4.77
    },
    {
     "year":2017,
     "value":4.78
    },
    {
     "year":2018,
     "value":4.57
    },
    {
     "year":2019,
     "value":4.37
    }
   ]
  },
  {
   "indicator":"surveillancecapacity_survcap",
   "yearlyData":[
    {
     "year":2018,
     "value":90.0
    },
    {
     "year":2020,
     "value":90.0
    }
   ]
  },
  {
   "indicator":"totalworkforceinmentalhealthsector_mhstotwf",
   "yearlyData":[
    {
     "year":2016,
     "value":21.62
    }
   ]
  },
  {
   "indicator":"transgenderpeoplepopulationsizeestimate_transgp",
   "yearlyData":[
    {
     "year":2016,
     "value":400.0
    }
   ]
  }
 ]
}